{
  "accUserMode" : 2,
  "getCapPSLanguageRes" : {
    "lanResTag" : "DE.LNAME.MEMBER"
  },
  "caption" : "成员",
  "codeName" : "member_portfolio_resource_mpick_up_grid_view",
  "dynaModelFilePath" : "PSSYSAPPS/plmweb/PSAPPDEVIEWS/member_portfolio_resource_mpick_up_grid_view.json",
  "gridRowActiveMode" : 1,
  "name" : "memberportfolio_resource_mpick_up_grid_view",
  "getPSAppDataEntity" : {
    "modelref" : true,
    "path" : "PSSYSAPPS/plmweb/PSAPPDATAENTITIES/member.json"
  },
  "getPSAppModule" : {
    "modelref" : true,
    "path" : "PSSYSAPPS/plmweb/PSAPPMODULES/Base.json"
  },
  "getPSAppViewEngines" : [ {
    "engineCat" : "VIEW",
    "engineType" : "PickupGridView",
    "name" : "engine"
  } ],
  "getPSControls" : [ {
    "aggMode" : "NONE",
    "codeName" : "resource_mpick_up_grid",
    "columnEnableFilter" : 2,
    "columnEnableLink" : 2,
    "controlType" : "GRID",
    "dynaModelFilePath" : "PSSYSAPPS/plmweb/PSAPPDATAENTITIES/member/PSGRIDS/resource_mpick_up_grid.json",
    "getFetchPSControlAction" : {
      "modelref" : true,
      "id" : "fetch",
      "actionType" : "DEDATASET",
      "name" : "fetch",
      "getPSAppDEMethod" : {
        "modelref" : true,
        "id" : "fetch_choose_portfolio_resource"
      },
      "getPSAppDataEntity" : {
        "modelref" : true,
        "path" : "PSSYSAPPS/plmweb/PSAPPDATAENTITIES/member.json"
      }
    },
    "groupMode" : "NONE",
    "logicName" : "资源成员多项选择视图_表格",
    "getPSAppDataEntity" : {
      "modelref" : true,
      "path" : "PSSYSAPPS/plmweb/PSAPPDATAENTITIES/member.json"
    },
    "getPSControlHandler" : {
      "getPSHandlerActions" : [ {
        "actionName" : "Get",
        "actionType" : "DEACTION",
        "dataAccessAction" : "READ",
        "name" : "load",
        "getPSAppDEMethod" : {
          "modelref" : true,
          "id" : "get"
        },
        "getPSAppDataEntity" : {
          "modelref" : true,
          "path" : "PSSYSAPPS/plmweb/PSAPPDATAENTITIES/member.json"
        }
      }, {
        "actionName" : "Create",
        "actionType" : "DEACTION",
        "dataAccessAction" : "CREATE",
        "name" : "create",
        "getPSAppDEMethod" : {
          "modelref" : true,
          "id" : "create"
        },
        "getPSAppDataEntity" : {
          "modelref" : true,
          "path" : "PSSYSAPPS/plmweb/PSAPPDATAENTITIES/member.json"
        }
      }, {
        "actionName" : "Update",
        "actionType" : "DEACTION",
        "dataAccessAction" : "UPDATE",
        "name" : "update",
        "getPSAppDEMethod" : {
          "modelref" : true,
          "id" : "update"
        },
        "getPSAppDataEntity" : {
          "modelref" : true,
          "path" : "PSSYSAPPS/plmweb/PSAPPDATAENTITIES/member.json"
        }
      }, {
        "actionName" : "Remove",
        "actionType" : "DEACTION",
        "dataAccessAction" : "DELETE",
        "name" : "remove",
        "getPSAppDEMethod" : {
          "modelref" : true,
          "id" : "remove"
        },
        "getPSAppDataEntity" : {
          "modelref" : true,
          "path" : "PSSYSAPPS/plmweb/PSAPPDATAENTITIES/member.json"
        }
      }, {
        "actionName" : "GetDraft",
        "actionType" : "DEACTION",
        "dataAccessAction" : "CREATE",
        "name" : "loaddraft",
        "getPSAppDEMethod" : {
          "modelref" : true,
          "id" : "get_draft"
        },
        "getPSAppDataEntity" : {
          "modelref" : true,
          "path" : "PSSYSAPPS/plmweb/PSAPPDATAENTITIES/member.json"
        }
      }, {
        "actionType" : "DEDATASET",
        "name" : "fetch",
        "getPSAppDEMethod" : {
          "modelref" : true,
          "id" : "fetch_choose_portfolio_resource"
        },
        "getPSAppDataEntity" : {
          "modelref" : true,
          "path" : "PSSYSAPPS/plmweb/PSAPPDATAENTITIES/member.json"
        }
      } ],
      "userDRAction" : "READ",
      "enableDEFieldPrivilege" : false,
      "id" : "数据表格处理器"
    },
    "getPSControlParam" : {
      "autoLoad" : true,
      "showBusyIndicator" : true,
      "id" : "GRID"
    },
    "getPSDEGridColumns" : [ {
      "align" : "LEFT",
      "cLConvertMode" : "NONE",
      "getCapPSLanguageRes" : {
        "lanResTag" : "DEF.LNAME.NAME"
      },
      "caption" : "成员",
      "codeName" : "name",
      "columnType" : "DEFGRIDCOLUMN",
      "dataItemName" : "name",
      "excelCaption" : "成员",
      "name" : "name",
      "noPrivDisplayMode" : 1,
      "getPSAppDEField" : {
        "name" : "NAME",
        "codeName" : "name"
      },
      "width" : 150,
      "widthUnit" : "PX",
      "enableSort" : false
    } ],
    "getPSDEGridDataItems" : [ {
      "dataType" : 25,
      "name" : "name",
      "getPSAppDEField" : {
        "name" : "NAME",
        "codeName" : "name"
      }
    }, {
      "dataType" : 25,
      "name" : "user_id",
      "getPSAppDEField" : {
        "name" : "USER_ID",
        "codeName" : "user_id"
      }
    }, {
      "dataType" : 25,
      "name" : "srfkey",
      "getPSAppDEField" : {
        "name" : "ID",
        "codeName" : "id"
      }
    }, {
      "dataType" : 25,
      "name" : "srfdataaccaction",
      "getPSAppDEField" : {
        "name" : "ID",
        "codeName" : "id"
      },
      "dataAccessAction" : true
    }, {
      "dataType" : 25,
      "name" : "position_id",
      "getPSAppDEField" : {
        "name" : "POSITION_ID",
        "codeName" : "position_id"
      }
    }, {
      "dataType" : 25,
      "name" : "srfmajortext",
      "getPSAppDEField" : {
        "name" : "NAME",
        "codeName" : "name"
      }
    } ],
    "getPSDEGridEditItems" : [ {
      "caption" : "标识",
      "codeName" : "srfkey",
      "enableCond" : 3,
      "ignoreInput" : 0,
      "name" : "srfkey",
      "getPSAppDEField" : {
        "name" : "ID",
        "codeName" : "id"
      },
      "getPSEditor" : {
        "editorType" : "HIDDEN",
        "name" : "srfkey"
      },
      "allowEmpty" : true
    } ],
    "pagingSize" : 20,
    "getRemovePSControlAction" : {
      "actionName" : "Remove",
      "actionType" : "DEACTION",
      "dataAccessAction" : "DELETE",
      "name" : "remove",
      "getPSAppDEMethod" : {
        "modelref" : true,
        "id" : "remove"
      },
      "getPSAppDataEntity" : {
        "modelref" : true,
        "path" : "PSSYSAPPS/plmweb/PSAPPDATAENTITIES/member.json"
      }
    },
    "sortMode" : "REMOTE",
    "hasWFDataItems" : false,
    "enableColFilter" : false,
    "enableCustomized" : false,
    "enableGroup" : false,
    "enablePagingBar" : false,
    "enableRowEdit" : false,
    "enableRowEditOrder" : false,
    "enableRowNew" : false,
    "forceFit" : false,
    "hideHeader" : false,
    "noSort" : false,
    "singleSelect" : true,
    "name" : "grid",
    "modelid" : "7581e4210f43dd9d2c1de23f4de4a204",
    "modeltype" : "PSDEGRID"
  }, {
    "codeName" : "usr05300875_search_form",
    "controlType" : "SEARCHFORM",
    "defaultLabelWidth" : 130,
    "dynaModelFilePath" : "PSSYSAPPS/plmweb/PSAPPDATAENTITIES/member/PSSEARCHFORMS/usr05300875_search_form.json",
    "logicName" : "资源成员多项选择视图_选择数据视图_搜索表单",
    "getPSAppDataEntity" : {
      "modelref" : true,
      "path" : "PSSYSAPPS/plmweb/PSAPPDATAENTITIES/member.json"
    },
    "getPSControlHandler" : {
      "getPSHandlerActions" : [ {
        "actionType" : "FILTERACTION",
        "name" : "load",
        "getPSAppDEMethod" : {
          "modelref" : true,
          "id" : "FilterGet"
        },
        "getPSAppDataEntity" : {
          "modelref" : true,
          "path" : "PSSYSAPPS/plmweb/PSAPPDATAENTITIES/member.json"
        }
      }, {
        "actionType" : "FILTERACTION",
        "name" : "loaddraft",
        "getPSAppDEMethod" : {
          "modelref" : true,
          "id" : "FilterGetDraft"
        },
        "getPSAppDataEntity" : {
          "modelref" : true,
          "path" : "PSSYSAPPS/plmweb/PSAPPDATAENTITIES/member.json"
        }
      }, {
        "actionType" : "FILTERACTION",
        "name" : "search",
        "getPSAppDEMethod" : {
          "modelref" : true,
          "id" : "FilterSearch"
        },
        "getPSAppDataEntity" : {
          "modelref" : true,
          "path" : "PSSYSAPPS/plmweb/PSAPPDATAENTITIES/member.json"
        }
      } ],
      "enableDEFieldPrivilege" : false,
      "id" : "搜索表单处理器"
    },
    "getPSControlParam" : {
      "autoLoad" : true,
      "showBusyIndicator" : true,
      "id" : "SEARCHFORM"
    },
    "getPSDEFormItems" : [ {
      "id" : "n_name_like",
      "dataType" : 25,
      "getPSAppDEField" : {
        "name" : "NAME",
        "codeName" : "name"
      }
    } ],
    "getPSDEFormPages" : [ {
      "caption" : "常规条件",
      "codeName" : "formpage1",
      "detailStyle" : "DEFAULT",
      "detailType" : "FORMPAGE",
      "name" : "formpage1",
      "getPSDEFormDetails" : [ {
        "getCapPSLanguageRes" : {
          "lanResTag" : "CONTROL.DEFSFITEM.MEMBER.N_NAME_LIKE"
        },
        "caption" : "名称",
        "codeName" : "n_name_like",
        "dataType" : 25,
        "detailStyle" : "DEFAULT",
        "detailType" : "FORMITEM",
        "enableCond" : 3,
        "ignoreInput" : 0,
        "labelPos" : "NONE",
        "labelWidth" : 0,
        "name" : "n_name_like",
        "noPrivDisplayMode" : 1,
        "getPSAppDEField" : {
          "name" : "NAME",
          "codeName" : "name"
        },
        "getPSEditor" : {
          "editorType" : "TEXTBOX",
          "name" : "n_name_like",
          "placeHolder" : "请输入查询姓名"
        },
        "getPSLayoutPos" : {
          "colLG" : 8,
          "colMD" : 8,
          "layout" : "TABLE_24COL"
        },
        "allowEmpty" : true
      } ],
      "getPSLayout" : {
        "childColLG" : 8,
        "childColMD" : 8,
        "columnCount" : 24,
        "layout" : "TABLE_24COL"
      },
      "infoGroupMode" : false
    } ],
    "getPSLayout" : {
      "childColMD" : 24,
      "columnCount" : 24,
      "layout" : "TABLE_24COL"
    },
    "searchButtonStyle" : "DEFAULT",
    "tabHeaderPos" : "TOP",
    "enableAdvanceSearch" : false,
    "enableAutoSearch" : true,
    "enableFilterSave" : false,
    "noTabHeader" : true,
    "name" : "searchform",
    "modelid" : "2ba4f1c83d744a0b2707894582536b2a",
    "modeltype" : "PSDEFORM_SEARCHFORM"
  }, {
    "controlType" : "SEARCHBAR",
    "name" : "searchbar",
    "getPSAppDataEntity" : {
      "modelref" : true,
      "path" : "PSSYSAPPS/plmweb/PSAPPDATAENTITIES/member.json"
    },
    "getPSControlParam" : {
      "id" : "searchbar"
    },
    "quickGroupCount" : -1,
    "quickSearchMode" : 0,
    "quickSearchWidth" : 0,
    "enableFilter" : false,
    "enableGroup" : false,
    "enableQuickSearch" : false,
    "mobileSearchBar" : false
  }, {
    "getCapPSLanguageRes" : {
      "lanResTag" : "DE.LNAME.MEMBER"
    },
    "caption" : "成员",
    "codeName" : "portfolio_resource_mpick_up_grid_view_captionbar",
    "controlType" : "CAPTIONBAR",
    "name" : "captionbar",
    "getPSAppDataEntity" : {
      "modelref" : true,
      "path" : "PSSYSAPPS/plmweb/PSAPPDATAENTITIES/member.json"
    },
    "getPSControlParam" : { }
  } ],
  "getPSDEViewCodeName" : "portfolio_resource_mpick_up_grid_view",
  "getPSDEViewId" : "9b20e766f8d45fa168cb46adf8945454",
  "getPSViewLayoutPanel" : {
    "codeName" : "layoutpanel",
    "controlStyle" : "APPDEPICKUPGRIDVIEW",
    "controlType" : "VIEWLAYOUTPANEL",
    "name" : "layoutpanel",
    "getPSAppDataEntity" : {
      "modelref" : true,
      "path" : "PSSYSAPPS/plmweb/PSAPPDATAENTITIES/member.json"
    },
    "getPSControlParam" : { },
    "layoutBodyOnly" : true,
    "layoutPanel" : true,
    "useDefaultLayout" : true
  },
  "refFlag" : false,
  "title" : "项目集资源成员选择",
  "viewStyle" : "DEFAULT",
  "viewType" : "DEPICKUPGRIDVIEW",
  "xDataControlName" : "grid",
  "enableDP" : true,
  "enableExport" : true,
  "enableFilter" : true,
  "enableImport" : true,
  "enableRowEdit" : false,
  "enableSearch" : true,
  "expandSearchForm" : true,
  "pickupMode" : true,
  "rowEditDefault" : false,
  "modelid" : "e8f76cd9a1563bfa612c0be3590d97de",
  "modeltype" : "PSAPPDEVIEW",
  "getPSAppDERSPaths" : [ [ {
    "actionRSMode" : 1,
    "codeName" : "article_pages",
    "dataRSMode" : 0,
    "majorDECodeName" : "shared_space",
    "majorDEName" : "SHARED_SPACE",
    "getMajorPSAppDataEntity" : {
      "modelref" : true,
      "path" : "PSSYSAPPS/plmweb/PSAPPDATAENTITIES/shared_space.json"
    },
    "minorDECodeName" : "article_page",
    "minorDEName" : "PAGE",
    "getMinorPSAppDataEntity" : {
      "modelref" : true,
      "path" : "PSSYSAPPS/plmweb/PSAPPDATAENTITIES/article_page.json"
    },
    "name" : "DERCUSTOM_SHARED_SPACE_PAGE",
    "getParentPSAppDEField" : {
      "name" : "SPACE_ID",
      "codeName" : "space_id"
    },
    "rSMode" : 2
  }, {
    "actionRSMode" : 1,
    "codeName" : "members",
    "dataRSMode" : 0,
    "majorDECodeName" : "article_page",
    "majorDEName" : "PAGE",
    "getMajorPSAppDataEntity" : {
      "modelref" : true,
      "path" : "PSSYSAPPS/plmweb/PSAPPDATAENTITIES/article_page.json"
    },
    "minorDECodeName" : "member",
    "minorDEName" : "MEMBER",
    "getMinorPSAppDataEntity" : {
      "modelref" : true,
      "path" : "PSSYSAPPS/plmweb/PSAPPDATAENTITIES/member.json"
    },
    "name" : "DERCUSTOM_MEMBER_PAGE_OWNER_ID",
    "getParentPSAppDEField" : {
      "name" : "OWNER_ID",
      "codeName" : "owner_id"
    },
    "rSMode" : 2
  } ], [ {
    "actionRSMode" : 1,
    "codeName" : "pages",
    "dataRSMode" : 0,
    "majorDECodeName" : "space",
    "majorDEName" : "SPACE",
    "getMajorPSAppDataEntity" : {
      "modelref" : true,
      "path" : "PSSYSAPPS/plmweb/PSAPPDATAENTITIES/space.json"
    },
    "minorDECodeName" : "article_page",
    "minorDEName" : "PAGE",
    "getMinorPSAppDataEntity" : {
      "modelref" : true,
      "path" : "PSSYSAPPS/plmweb/PSAPPDATAENTITIES/article_page.json"
    },
    "name" : "DER1N_PAGE_SPACE_SPACE_ID",
    "getParentPSAppDEField" : {
      "name" : "SPACE_ID",
      "codeName" : "space_id"
    },
    "getParentTextPSAppDEField" : {
      "name" : "SPACE_NAME",
      "codeName" : "space_name"
    },
    "rSMode" : 2
  }, {
    "actionRSMode" : 1,
    "codeName" : "members",
    "dataRSMode" : 0,
    "majorDECodeName" : "article_page",
    "majorDEName" : "PAGE",
    "getMajorPSAppDataEntity" : {
      "modelref" : true,
      "path" : "PSSYSAPPS/plmweb/PSAPPDATAENTITIES/article_page.json"
    },
    "minorDECodeName" : "member",
    "minorDEName" : "MEMBER",
    "getMinorPSAppDataEntity" : {
      "modelref" : true,
      "path" : "PSSYSAPPS/plmweb/PSAPPDATAENTITIES/member.json"
    },
    "name" : "DERCUSTOM_MEMBER_PAGE_OWNER_ID",
    "getParentPSAppDEField" : {
      "name" : "OWNER_ID",
      "codeName" : "owner_id"
    },
    "rSMode" : 2
  } ], [ {
    "actionRSMode" : 1,
    "codeName" : "groups",
    "dataRSMode" : 0,
    "majorDECodeName" : "section",
    "majorDEName" : "SECTION",
    "getMajorPSAppDataEntity" : {
      "modelref" : true,
      "path" : "PSSYSAPPS/plmweb/PSAPPDATAENTITIES/section.json"
    },
    "minorDECodeName" : "group",
    "minorDEName" : "GROUP",
    "getMinorPSAppDataEntity" : {
      "modelref" : true,
      "path" : "PSSYSAPPS/plmweb/PSAPPDATAENTITIES/group.json"
    },
    "name" : "DER1N_GROUP_SECTION_SECTION_ID",
    "getParentPSAppDEField" : {
      "name" : "SECTION_ID",
      "codeName" : "section_id"
    },
    "getParentTextPSAppDEField" : {
      "name" : "SECTION_NAME",
      "codeName" : "section_name"
    },
    "rSMode" : 2
  }, {
    "actionRSMode" : 1,
    "codeName" : "members",
    "dataRSMode" : 0,
    "majorDECodeName" : "group",
    "majorDEName" : "GROUP",
    "getMajorPSAppDataEntity" : {
      "modelref" : true,
      "path" : "PSSYSAPPS/plmweb/PSAPPDATAENTITIES/group.json"
    },
    "minorDECodeName" : "member",
    "minorDEName" : "MEMBER",
    "getMinorPSAppDataEntity" : {
      "modelref" : true,
      "path" : "PSSYSAPPS/plmweb/PSAPPDATAENTITIES/member.json"
    },
    "name" : "DERCUSTOM_MEMBER_GROUP_OWNER_ID",
    "getParentPSAppDEField" : {
      "name" : "OWNER_ID",
      "codeName" : "owner_id"
    },
    "rSMode" : 2
  } ], [ {
    "actionRSMode" : 1,
    "codeName" : "members",
    "dataRSMode" : 0,
    "majorDECodeName" : "project",
    "majorDEName" : "PROJECT",
    "getMajorPSAppDataEntity" : {
      "modelref" : true,
      "path" : "PSSYSAPPS/plmweb/PSAPPDATAENTITIES/project.json"
    },
    "minorDECodeName" : "member",
    "minorDEName" : "MEMBER",
    "getMinorPSAppDataEntity" : {
      "modelref" : true,
      "path" : "PSSYSAPPS/plmweb/PSAPPDATAENTITIES/member.json"
    },
    "name" : "DERCUSTOM_MEMBER_PROJECT_OWNER_ID",
    "getParentPSAppDEField" : {
      "name" : "OWNER_ID",
      "codeName" : "owner_id"
    },
    "rSMode" : 2
  } ], [ {
    "actionRSMode" : 1,
    "codeName" : "members",
    "dataRSMode" : 0,
    "majorDECodeName" : "article_page",
    "majorDEName" : "PAGE",
    "getMajorPSAppDataEntity" : {
      "modelref" : true,
      "path" : "PSSYSAPPS/plmweb/PSAPPDATAENTITIES/article_page.json"
    },
    "minorDECodeName" : "member",
    "minorDEName" : "MEMBER",
    "getMinorPSAppDataEntity" : {
      "modelref" : true,
      "path" : "PSSYSAPPS/plmweb/PSAPPDATAENTITIES/member.json"
    },
    "name" : "DERCUSTOM_MEMBER_PAGE_OWNER_ID",
    "getParentPSAppDEField" : {
      "name" : "OWNER_ID",
      "codeName" : "owner_id"
    },
    "rSMode" : 2
  } ], [ {
    "actionRSMode" : 1,
    "codeName" : "members",
    "dataRSMode" : 0,
    "majorDECodeName" : "group",
    "majorDEName" : "GROUP",
    "getMajorPSAppDataEntity" : {
      "modelref" : true,
      "path" : "PSSYSAPPS/plmweb/PSAPPDATAENTITIES/group.json"
    },
    "minorDECodeName" : "member",
    "minorDEName" : "MEMBER",
    "getMinorPSAppDataEntity" : {
      "modelref" : true,
      "path" : "PSSYSAPPS/plmweb/PSAPPDATAENTITIES/member.json"
    },
    "name" : "DERCUSTOM_MEMBER_GROUP_OWNER_ID",
    "getParentPSAppDEField" : {
      "name" : "OWNER_ID",
      "codeName" : "owner_id"
    },
    "rSMode" : 2
  } ] ]
}