{
  "codeName" : "save_workload",
  "defaultParamName" : "Default",
  "dynaModelFilePath" : "PSMODULES/Base/PSDATAENTITIES/workload/PSDELOGICS/save_workload.json",
  "logicName" : "登记工时并更新剩余工时",
  "memo" : "保存实际登记工时记录，并计算重置剩余工时属性",
  "name" : "登记工时并更新剩余工时",
  "getPSDELogicNodes" : [ {
    "codeName" : "Begin",
    "leftPos" : 200,
    "logicNodeType" : "BEGIN",
    "name" : "开始",
    "getPSDELogicLinks" : [ {
      "getDstPSDELogicNode" : {
        "modelref" : true,
        "id" : "DEBUGPARAM1"
      },
      "name" : "连接名称",
      "getSrcPSDELogicNode" : {
        "modelref" : true,
        "id" : "Begin"
      }
    } ],
    "topPos" : -90
  }, {
    "codeName" : "DEBUGPARAM1",
    "getDstPSDELogicParam" : {
      "modelref" : true,
      "id" : "Default"
    },
    "leftPos" : 160,
    "logicNodeType" : "DEBUGPARAM",
    "name" : "调试逻辑参数",
    "getPSDELogicLinks" : [ {
      "getDstPSDELogicNode" : {
        "modelref" : true,
        "id" : "PREPAREPARAM2"
      },
      "name" : "连接名称",
      "getSrcPSDELogicNode" : {
        "modelref" : true,
        "id" : "DEBUGPARAM1"
      }
    } ],
    "topPos" : 19
  }, {
    "codeName" : "PREPAREPARAM2",
    "leftPos" : 160,
    "logicNodeType" : "PREPAREPARAM",
    "name" : "绑定所属对象标识",
    "getPSDELogicLinks" : [ {
      "getDstPSDELogicNode" : {
        "modelref" : true,
        "id" : "DEACTION3"
      },
      "name" : "产品需求登记工时",
      "getPSDELogicLinkGroupCond" : {
        "groupOP" : "AND",
        "logicType" : "GROUP",
        "name" : "连接条件组",
        "getPSDELogicLinkConds" : [ {
          "condOP" : "EQ",
          "dstFieldName" : "workload_kind",
          "getDstLogicParam" : {
            "modelref" : true,
            "id" : "Default"
          },
          "logicType" : "SINGLE",
          "name" : "Default[workload_kind] 等于(=) 产品需求",
          "paramValue" : "产品需求"
        } ]
      },
      "getSrcPSDELogicNode" : {
        "modelref" : true,
        "id" : "PREPAREPARAM2"
      }
    }, {
      "getDstPSDELogicNode" : {
        "modelref" : true,
        "id" : "DEACTION4"
      },
      "name" : "工作项登记工时",
      "getPSDELogicLinkGroupCond" : {
        "groupOP" : "AND",
        "logicType" : "GROUP",
        "name" : "连接条件组",
        "getPSDELogicLinkConds" : [ {
          "condOP" : "EQ",
          "dstFieldName" : "workload_kind",
          "getDstLogicParam" : {
            "modelref" : true,
            "id" : "Default"
          },
          "logicType" : "SINGLE",
          "name" : "Default[workload_kind] 等于(=) 工作项",
          "paramValue" : "工作项"
        } ]
      },
      "getSrcPSDELogicNode" : {
        "modelref" : true,
        "id" : "PREPAREPARAM2"
      }
    }, {
      "getDstPSDELogicNode" : {
        "modelref" : true,
        "id" : "DEACTION5"
      },
      "name" : "测试用例登记工时",
      "getPSDELogicLinkGroupCond" : {
        "groupOP" : "AND",
        "logicType" : "GROUP",
        "name" : "连接条件组",
        "getPSDELogicLinkConds" : [ {
          "condOP" : "EQ",
          "dstFieldName" : "workload_kind",
          "getDstLogicParam" : {
            "modelref" : true,
            "id" : "Default"
          },
          "logicType" : "SINGLE",
          "name" : "Default[workload_kind] 等于(=) 测试用例",
          "paramValue" : "测试用例"
        } ]
      },
      "getSrcPSDELogicNode" : {
        "modelref" : true,
        "id" : "PREPAREPARAM2"
      }
    } ],
    "getPSDELogicNodeParams" : [ {
      "dstFieldName" : "ID",
      "getDstPSDELogicParam" : {
        "modelref" : true,
        "id" : "test_case"
      },
      "name" : "Default[PRINCIPAL_ID] ==> test_case[ID]",
      "paramAction" : "SETPARAMVALUE",
      "srcFieldName" : "PRINCIPAL_ID",
      "getSrcPSDELogicParam" : {
        "modelref" : true,
        "id" : "Default"
      },
      "srcValueType" : "SRCDLPARAM"
    }, {
      "dstFieldName" : "OWNER_ID",
      "getDstPSDELogicParam" : {
        "modelref" : true,
        "id" : "actual"
      },
      "name" : "Default[PRINCIPAL_ID] ==> actual[OWNER_ID]",
      "paramAction" : "SETPARAMVALUE",
      "srcFieldName" : "PRINCIPAL_ID",
      "getSrcPSDELogicParam" : {
        "modelref" : true,
        "id" : "Default"
      },
      "srcValueType" : "SRCDLPARAM"
    }, {
      "dstFieldName" : "OWNER_ID",
      "getDstPSDELogicParam" : {
        "modelref" : true,
        "id" : "actual"
      },
      "name" : "Default[PRINCIPAL_ID] ==> actual[OWNER_ID]",
      "paramAction" : "SETPARAMVALUE",
      "srcFieldName" : "PRINCIPAL_ID",
      "getSrcPSDELogicParam" : {
        "modelref" : true,
        "id" : "Default"
      },
      "srcValueType" : "SRCDLPARAM"
    }, {
      "dstFieldName" : "NAME",
      "getDstPSDELogicParam" : {
        "modelref" : true,
        "id" : "remaining"
      },
      "name" : "直接值[REMAINING_WORKLOAD] ==> remaining[NAME]",
      "paramAction" : "SETPARAMVALUE",
      "srcValue" : "REMAINING_WORKLOAD",
      "srcValueType" : "SRCVALUE"
    }, {
      "dstFieldName" : "OWNER_ID",
      "getDstPSDELogicParam" : {
        "modelref" : true,
        "id" : "remaining"
      },
      "name" : "Default[PRINCIPAL_ID] ==> remaining[OWNER_ID]",
      "paramAction" : "SETPARAMVALUE",
      "srcFieldName" : "PRINCIPAL_ID",
      "getSrcPSDELogicParam" : {
        "modelref" : true,
        "id" : "Default"
      },
      "srcValueType" : "SRCDLPARAM"
    }, {
      "dstFieldName" : "DECIMAL_VALUE",
      "getDstPSDELogicParam" : {
        "modelref" : true,
        "id" : "remaining"
      },
      "name" : "Default[REMAINING_WORKLOAD] ==> remaining[DECIMAL_VALUE]",
      "paramAction" : "SETPARAMVALUE",
      "srcFieldName" : "REMAINING_WORKLOAD",
      "getSrcPSDELogicParam" : {
        "modelref" : true,
        "id" : "Default"
      },
      "srcValueType" : "SRCDLPARAM"
    }, {
      "dstFieldName" : "ID",
      "getDstPSDELogicParam" : {
        "modelref" : true,
        "id" : "work_item"
      },
      "name" : "Default[PRINCIPAL_ID] ==> work_item[ID]",
      "paramAction" : "SETPARAMVALUE",
      "srcFieldName" : "PRINCIPAL_ID",
      "getSrcPSDELogicParam" : {
        "modelref" : true,
        "id" : "Default"
      },
      "srcValueType" : "SRCDLPARAM"
    }, {
      "dstFieldName" : "ID",
      "getDstPSDELogicParam" : {
        "modelref" : true,
        "id" : "idea"
      },
      "name" : "Default[PRINCIPAL_ID] ==> idea[ID]",
      "paramAction" : "SETPARAMVALUE",
      "srcFieldName" : "PRINCIPAL_ID",
      "getSrcPSDELogicParam" : {
        "modelref" : true,
        "id" : "Default"
      },
      "srcValueType" : "SRCDLPARAM"
    } ],
    "topPos" : 160
  }, {
    "codeName" : "DEACTION3",
    "getDstPSDEAction" : {
      "modelref" : true,
      "path" : "PSMODULES/ProdMgmt/PSDATAENTITIES/idea/PSDEACTIONS/Get.json"
    },
    "getDstPSDELogicParam" : {
      "modelref" : true,
      "id" : "idea"
    },
    "getDstPSDataEntity" : {
      "modelref" : true,
      "path" : "PSMODULES/ProdMgmt/PSDATAENTITIES/idea.json"
    },
    "leftPos" : -90,
    "logicNodeType" : "DEACTION",
    "name" : "获取需求",
    "getPSDELogicLinks" : [ {
      "getDstPSDELogicNode" : {
        "modelref" : true,
        "id" : "PREPAREPARAM4"
      },
      "name" : "连接名称",
      "getSrcPSDELogicNode" : {
        "modelref" : true,
        "id" : "DEACTION3"
      }
    } ],
    "getRetPSDELogicParam" : {
      "modelref" : true,
      "id" : "idea"
    },
    "topPos" : 330
  }, {
    "codeName" : "DEACTION4",
    "getDstPSDEAction" : {
      "modelref" : true,
      "path" : "PSMODULES/ProjMgmt/PSDATAENTITIES/work_item/PSDEACTIONS/Get.json"
    },
    "getDstPSDELogicParam" : {
      "modelref" : true,
      "id" : "work_item"
    },
    "getDstPSDataEntity" : {
      "modelref" : true,
      "path" : "PSMODULES/ProjMgmt/PSDATAENTITIES/work_item.json"
    },
    "leftPos" : 160,
    "logicNodeType" : "DEACTION",
    "name" : "获取工作项",
    "getPSDELogicLinks" : [ {
      "getDstPSDELogicNode" : {
        "modelref" : true,
        "id" : "PREPAREPARAM3"
      },
      "name" : "连接名称",
      "getSrcPSDELogicNode" : {
        "modelref" : true,
        "id" : "DEACTION4"
      }
    } ],
    "getRetPSDELogicParam" : {
      "modelref" : true,
      "id" : "work_item"
    },
    "topPos" : 330
  }, {
    "codeName" : "DEACTION5",
    "getDstPSDEAction" : {
      "modelref" : true,
      "path" : "PSMODULES/TestMgmt/PSDATAENTITIES/test_case/PSDEACTIONS/Get.json"
    },
    "getDstPSDELogicParam" : {
      "modelref" : true,
      "id" : "test_case"
    },
    "getDstPSDataEntity" : {
      "modelref" : true,
      "path" : "PSMODULES/TestMgmt/PSDATAENTITIES/test_case.json"
    },
    "leftPos" : 433,
    "logicNodeType" : "DEACTION",
    "name" : "获取测试用例",
    "getPSDELogicLinks" : [ {
      "getDstPSDELogicNode" : {
        "modelref" : true,
        "id" : "PREPAREPARAM5"
      },
      "name" : "连接名称",
      "getSrcPSDELogicNode" : {
        "modelref" : true,
        "id" : "DEACTION5"
      }
    } ],
    "getRetPSDELogicParam" : {
      "modelref" : true,
      "id" : "test_case"
    },
    "topPos" : 330
  }, {
    "codeName" : "PREPAREPARAM3",
    "leftPos" : 160,
    "logicNodeType" : "PREPAREPARAM",
    "name" : "工作项和项目信息属性",
    "getPSDELogicLinks" : [ {
      "getDstPSDELogicNode" : {
        "modelref" : true,
        "id" : "DEACTION2"
      },
      "name" : "连接名称",
      "getSrcPSDELogicNode" : {
        "modelref" : true,
        "id" : "PREPAREPARAM3"
      }
    } ],
    "getPSDELogicNodeParams" : [ {
      "dstFieldName" : "IDENTIFIER",
      "getDstPSDELogicParam" : {
        "modelref" : true,
        "id" : "Default"
      },
      "name" : "work_item[IDENTIFIER] ==> Default[IDENTIFIER]",
      "paramAction" : "SETPARAMVALUE",
      "srcFieldName" : "IDENTIFIER",
      "getSrcPSDELogicParam" : {
        "modelref" : true,
        "id" : "work_item"
      },
      "srcValueType" : "SRCDLPARAM"
    }, {
      "dstFieldName" : "NAME",
      "getDstPSDELogicParam" : {
        "modelref" : true,
        "id" : "actual"
      },
      "name" : "Default[CATEGORY] ==> actual[NAME]",
      "paramAction" : "SETPARAMVALUE",
      "srcFieldName" : "CATEGORY",
      "getSrcPSDELogicParam" : {
        "modelref" : true,
        "id" : "Default"
      },
      "srcValue" : "ACTUAL_WORKLOAD",
      "srcValueType" : "SRCDLPARAM"
    }, {
      "dstFieldName" : "OWNER_TYPE",
      "getDstPSDELogicParam" : {
        "modelref" : true,
        "id" : "actual"
      },
      "name" : "直接值[WORK_ITEM] ==> actual[OWNER_TYPE]",
      "paramAction" : "SETPARAMVALUE",
      "srcValue" : "WORK_ITEM",
      "srcValueType" : "SRCVALUE"
    }, {
      "dstFieldName" : "OWNER_TYPE",
      "getDstPSDELogicParam" : {
        "modelref" : true,
        "id" : "remaining"
      },
      "name" : "直接值[WORK_ITEM] ==> remaining[OWNER_TYPE]",
      "paramAction" : "SETPARAMVALUE",
      "srcValue" : "WORK_ITEM",
      "srcValueType" : "SRCVALUE"
    }, {
      "dstFieldName" : "PRINCIPAL_TYPE",
      "getDstPSDELogicParam" : {
        "modelref" : true,
        "id" : "Default"
      },
      "name" : "直接值[WORK_ITEM] ==> Default[PRINCIPAL_TYPE]",
      "paramAction" : "SETPARAMVALUE",
      "srcValue" : "WORK_ITEM",
      "srcValueType" : "SRCVALUE"
    }, {
      "dstFieldName" : "RECENT_PARENT",
      "getDstPSDELogicParam" : {
        "modelref" : true,
        "id" : "Default"
      },
      "name" : "work_item[PROJECT_ID] ==> Default[RECENT_PARENT]",
      "paramAction" : "SETPARAMVALUE",
      "srcFieldName" : "PROJECT_ID",
      "getSrcPSDELogicParam" : {
        "modelref" : true,
        "id" : "work_item"
      },
      "srcValueType" : "SRCDLPARAM"
    }, {
      "dstFieldName" : "RECENT_PARENT_IDENTIFIER",
      "getDstPSDELogicParam" : {
        "modelref" : true,
        "id" : "Default"
      },
      "name" : "work_item[PROJECT_IDENTIFIER] ==> Default[RECENT_PARENT_IDENTIFIER]",
      "paramAction" : "SETPARAMVALUE",
      "srcFieldName" : "PROJECT_IDENTIFIER",
      "getSrcPSDELogicParam" : {
        "modelref" : true,
        "id" : "work_item"
      },
      "srcValueType" : "SRCDLPARAM"
    }, {
      "dstFieldName" : "RECENT_PARENT_NAME",
      "getDstPSDELogicParam" : {
        "modelref" : true,
        "id" : "Default"
      },
      "name" : "work_item[PROJECT_NAME] ==> Default[RECENT_PARENT_NAME]",
      "paramAction" : "SETPARAMVALUE",
      "srcFieldName" : "PROJECT_NAME",
      "getSrcPSDELogicParam" : {
        "modelref" : true,
        "id" : "work_item"
      },
      "srcValueType" : "SRCDLPARAM"
    }, {
      "dstFieldName" : "NAME",
      "getDstPSDELogicParam" : {
        "modelref" : true,
        "id" : "Default"
      },
      "name" : "work_item[TITLE] ==> Default[NAME]",
      "paramAction" : "SETPARAMVALUE",
      "srcFieldName" : "TITLE",
      "getSrcPSDELogicParam" : {
        "modelref" : true,
        "id" : "work_item"
      },
      "srcValueType" : "SRCDLPARAM"
    } ],
    "topPos" : 430
  }, {
    "codeName" : "PREPAREPARAM4",
    "leftPos" : -90,
    "logicNodeType" : "PREPAREPARAM",
    "name" : "产品需求和产品信息属性",
    "getPSDELogicLinks" : [ {
      "getDstPSDELogicNode" : {
        "modelref" : true,
        "id" : "DEACTION2"
      },
      "name" : "连接名称",
      "getSrcPSDELogicNode" : {
        "modelref" : true,
        "id" : "PREPAREPARAM4"
      }
    } ],
    "getPSDELogicNodeParams" : [ {
      "dstFieldName" : "IDENTIFIER",
      "getDstPSDELogicParam" : {
        "modelref" : true,
        "id" : "Default"
      },
      "name" : "idea[IDENTIFIER] ==> Default[IDENTIFIER]",
      "paramAction" : "SETPARAMVALUE",
      "srcFieldName" : "IDENTIFIER",
      "getSrcPSDELogicParam" : {
        "modelref" : true,
        "id" : "idea"
      },
      "srcValueType" : "SRCDLPARAM"
    }, {
      "dstFieldName" : "OWNER_TYPE",
      "getDstPSDELogicParam" : {
        "modelref" : true,
        "id" : "actual"
      },
      "name" : "直接值[IDEA] ==> actual[OWNER_TYPE]",
      "paramAction" : "SETPARAMVALUE",
      "srcValue" : "IDEA",
      "srcValueType" : "SRCVALUE"
    }, {
      "dstFieldName" : "NAME",
      "getDstPSDELogicParam" : {
        "modelref" : true,
        "id" : "actual"
      },
      "name" : "Default[CATEGORY] ==> actual[NAME]",
      "paramAction" : "SETPARAMVALUE",
      "srcFieldName" : "CATEGORY",
      "getSrcPSDELogicParam" : {
        "modelref" : true,
        "id" : "Default"
      },
      "srcValue" : "ACTUAL_WORKLOAD",
      "srcValueType" : "SRCDLPARAM"
    }, {
      "dstFieldName" : "OWNER_TYPE",
      "getDstPSDELogicParam" : {
        "modelref" : true,
        "id" : "remaining"
      },
      "name" : "直接值[IDEA] ==> remaining[OWNER_TYPE]",
      "paramAction" : "SETPARAMVALUE",
      "srcValue" : "IDEA",
      "srcValueType" : "SRCVALUE"
    }, {
      "dstFieldName" : "RECENT_PARENT",
      "getDstPSDELogicParam" : {
        "modelref" : true,
        "id" : "Default"
      },
      "name" : "idea[PRODUCT_ID] ==> Default[RECENT_PARENT]",
      "paramAction" : "SETPARAMVALUE",
      "srcFieldName" : "PRODUCT_ID",
      "getSrcPSDELogicParam" : {
        "modelref" : true,
        "id" : "idea"
      },
      "srcValueType" : "SRCDLPARAM"
    }, {
      "dstFieldName" : "RECENT_PARENT_NAME",
      "getDstPSDELogicParam" : {
        "modelref" : true,
        "id" : "Default"
      },
      "name" : "idea[PRODUCT_NAME] ==> Default[RECENT_PARENT_NAME]",
      "paramAction" : "SETPARAMVALUE",
      "srcFieldName" : "PRODUCT_NAME",
      "getSrcPSDELogicParam" : {
        "modelref" : true,
        "id" : "idea"
      },
      "srcValueType" : "SRCDLPARAM"
    }, {
      "dstFieldName" : "RECENT_PARENT_IDENTIFIER",
      "getDstPSDELogicParam" : {
        "modelref" : true,
        "id" : "Default"
      },
      "name" : "idea[PRODUCT_IDENTIFIER] ==> Default[RECENT_PARENT_IDENTIFIER]",
      "paramAction" : "SETPARAMVALUE",
      "srcFieldName" : "PRODUCT_IDENTIFIER",
      "getSrcPSDELogicParam" : {
        "modelref" : true,
        "id" : "idea"
      },
      "srcValueType" : "SRCDLPARAM"
    }, {
      "dstFieldName" : "NAME",
      "getDstPSDELogicParam" : {
        "modelref" : true,
        "id" : "Default"
      },
      "name" : "idea[TITLE] ==> Default[NAME]",
      "paramAction" : "SETPARAMVALUE",
      "srcFieldName" : "TITLE",
      "getSrcPSDELogicParam" : {
        "modelref" : true,
        "id" : "idea"
      },
      "srcValueType" : "SRCDLPARAM"
    }, {
      "dstFieldName" : "PRINCIPAL_TYPE",
      "getDstPSDELogicParam" : {
        "modelref" : true,
        "id" : "Default"
      },
      "name" : "直接值[IDEA] ==> Default[PRINCIPAL_TYPE]",
      "paramAction" : "SETPARAMVALUE",
      "srcValue" : "IDEA",
      "srcValueType" : "SRCVALUE"
    } ],
    "topPos" : 430
  }, {
    "codeName" : "PREPAREPARAM5",
    "leftPos" : 433,
    "logicNodeType" : "PREPAREPARAM",
    "name" : "测试用例和测试库信息属性",
    "getPSDELogicLinks" : [ {
      "getDstPSDELogicNode" : {
        "modelref" : true,
        "id" : "DEACTION2"
      },
      "name" : "连接名称",
      "getSrcPSDELogicNode" : {
        "modelref" : true,
        "id" : "PREPAREPARAM5"
      }
    } ],
    "getPSDELogicNodeParams" : [ {
      "dstFieldName" : "IDENTIFIER",
      "getDstPSDELogicParam" : {
        "modelref" : true,
        "id" : "Default"
      },
      "name" : "test_case[IDENTIFIER] ==> Default[IDENTIFIER]",
      "paramAction" : "SETPARAMVALUE",
      "srcFieldName" : "IDENTIFIER",
      "getSrcPSDELogicParam" : {
        "modelref" : true,
        "id" : "test_case"
      },
      "srcValueType" : "SRCDLPARAM"
    }, {
      "dstFieldName" : "OWNER_TYPE",
      "getDstPSDELogicParam" : {
        "modelref" : true,
        "id" : "actual"
      },
      "name" : "直接值[TEST_CASE] ==> actual[OWNER_TYPE]",
      "paramAction" : "SETPARAMVALUE",
      "srcValue" : "TEST_CASE",
      "srcValueType" : "SRCVALUE"
    }, {
      "dstFieldName" : "NAME",
      "getDstPSDELogicParam" : {
        "modelref" : true,
        "id" : "actual"
      },
      "name" : "Default[CATEGORY] ==> actual[NAME]",
      "paramAction" : "SETPARAMVALUE",
      "srcFieldName" : "CATEGORY",
      "getSrcPSDELogicParam" : {
        "modelref" : true,
        "id" : "Default"
      },
      "srcValue" : "ACTUAL_WORKLOAD",
      "srcValueType" : "SRCDLPARAM"
    }, {
      "dstFieldName" : "OWNER_TYPE",
      "getDstPSDELogicParam" : {
        "modelref" : true,
        "id" : "remaining"
      },
      "name" : "直接值[TEST_CASE] ==> remaining[OWNER_TYPE]",
      "paramAction" : "SETPARAMVALUE",
      "srcValue" : "TEST_CASE",
      "srcValueType" : "SRCVALUE"
    }, {
      "dstFieldName" : "RECENT_PARENT_IDENTIFIER",
      "getDstPSDELogicParam" : {
        "modelref" : true,
        "id" : "Default"
      },
      "name" : "test_case[LIBRARY_IDENTIFIER] ==> Default[RECENT_PARENT_IDENTIFIER]",
      "paramAction" : "SETPARAMVALUE",
      "srcFieldName" : "LIBRARY_IDENTIFIER",
      "getSrcPSDELogicParam" : {
        "modelref" : true,
        "id" : "test_case"
      },
      "srcValueType" : "SRCDLPARAM"
    }, {
      "dstFieldName" : "RECENT_PARENT",
      "getDstPSDELogicParam" : {
        "modelref" : true,
        "id" : "Default"
      },
      "name" : "test_case[TEST_LIBRARY_ID] ==> Default[RECENT_PARENT]",
      "paramAction" : "SETPARAMVALUE",
      "srcFieldName" : "TEST_LIBRARY_ID",
      "getSrcPSDELogicParam" : {
        "modelref" : true,
        "id" : "test_case"
      },
      "srcValueType" : "SRCDLPARAM"
    }, {
      "dstFieldName" : "NAME",
      "getDstPSDELogicParam" : {
        "modelref" : true,
        "id" : "Default"
      },
      "name" : "test_case[TEST_LIBRARY_NAME] ==> Default[NAME]",
      "paramAction" : "SETPARAMVALUE",
      "srcFieldName" : "TEST_LIBRARY_NAME",
      "getSrcPSDELogicParam" : {
        "modelref" : true,
        "id" : "test_case"
      },
      "srcValueType" : "SRCDLPARAM"
    }, {
      "dstFieldName" : "NAME",
      "getDstPSDELogicParam" : {
        "modelref" : true,
        "id" : "Default"
      },
      "name" : "test_case[TITLE] ==> Default[NAME]",
      "paramAction" : "SETPARAMVALUE",
      "srcFieldName" : "TITLE",
      "getSrcPSDELogicParam" : {
        "modelref" : true,
        "id" : "test_case"
      },
      "srcValueType" : "SRCDLPARAM"
    }, {
      "dstFieldName" : "PRINCIPAL_TYPE",
      "getDstPSDELogicParam" : {
        "modelref" : true,
        "id" : "Default"
      },
      "name" : "直接值[TEST_CASE] ==> Default[PRINCIPAL_TYPE]",
      "paramAction" : "SETPARAMVALUE",
      "srcValue" : "TEST_CASE",
      "srcValueType" : "SRCVALUE"
    } ],
    "topPos" : 430
  }, {
    "codeName" : "DEACTION2",
    "getDstPSDEAction" : {
      "modelref" : true,
      "path" : "PSMODULES/Base/PSDATAENTITIES/workload/PSDEACTIONS/Save.json"
    },
    "getDstPSDELogicParam" : {
      "modelref" : true,
      "id" : "Default"
    },
    "getDstPSDataEntity" : {
      "modelref" : true,
      "path" : "PSMODULES/Base/PSDATAENTITIES/workload.json"
    },
    "leftPos" : 160,
    "logicNodeType" : "DEACTION",
    "name" : "保存工时",
    "getPSDELogicLinks" : [ {
      "getDstPSDELogicNode" : {
        "modelref" : true,
        "id" : "DEACTION6"
      },
      "name" : "连接名称",
      "getSrcPSDELogicNode" : {
        "modelref" : true,
        "id" : "DEACTION2"
      }
    } ],
    "getRetPSDELogicParam" : {
      "modelref" : true,
      "id" : "Default"
    },
    "topPos" : 610
  }, {
    "codeName" : "DEACTION6",
    "getDstPSDEAction" : {
      "modelref" : true,
      "path" : "PSMODULES/Base/PSDATAENTITIES/extend_storage/PSDEACTIONS/Save.json"
    },
    "getDstPSDELogicParam" : {
      "modelref" : true,
      "id" : "remaining"
    },
    "getDstPSDataEntity" : {
      "modelref" : true,
      "path" : "PSMODULES/Base/PSDATAENTITIES/extend_storage.json"
    },
    "leftPos" : 160,
    "logicNodeType" : "DEACTION",
    "name" : "更新剩余工时",
    "getPSDELogicLinks" : [ {
      "getDstPSDELogicNode" : {
        "modelref" : true,
        "id" : "RAWSQLCALL1"
      },
      "name" : "连接名称",
      "getSrcPSDELogicNode" : {
        "modelref" : true,
        "id" : "DEACTION6"
      }
    } ],
    "topPos" : 750
  }, {
    "codeName" : "PREPAREPARAM6",
    "leftPos" : 460,
    "logicNodeType" : "PREPAREPARAM",
    "name" : "工时为0时置为NULL",
    "getPSDELogicLinks" : [ {
      "getDstPSDELogicNode" : {
        "modelref" : true,
        "id" : "DEACTION7"
      },
      "name" : "连接名称",
      "getSrcPSDELogicNode" : {
        "modelref" : true,
        "id" : "PREPAREPARAM6"
      }
    } ],
    "getPSDELogicNodeParams" : [ {
      "dstFieldName" : "DECIMAL_VALUE",
      "getDstPSDELogicParam" : {
        "modelref" : true,
        "id" : "actual"
      },
      "name" : "空值（NULL） ==> actual[DECIMAL_VALUE]",
      "paramAction" : "SETPARAMVALUE",
      "srcValueType" : "NULLVALUE"
    } ],
    "topPos" : 910
  }, {
    "codeName" : "RAWSQLCALL1",
    "getDstPSDELogicParam" : {
      "modelref" : true,
      "id" : "actual"
    },
    "leftPos" : 160,
    "logicNodeType" : "RAWSQLCALL",
    "name" : "合计已登记工时",
    "getPSDELogicLinks" : [ {
      "getDstPSDELogicNode" : {
        "modelref" : true,
        "id" : "DEACTION7"
      },
      "name" : "合计已登记工时大于0",
      "getPSDELogicLinkGroupCond" : {
        "groupOP" : "AND",
        "logicType" : "GROUP",
        "name" : "连接条件组",
        "getPSDELogicLinkConds" : [ {
          "condOP" : "NOTEQ",
          "dstFieldName" : "DECIMAL_VALUE",
          "getDstLogicParam" : {
            "modelref" : true,
            "id" : "actual"
          },
          "logicType" : "SINGLE",
          "name" : "actual[DECIMAL_VALUE] 不等于(<>) 0",
          "paramValue" : "0"
        } ]
      },
      "getSrcPSDELogicNode" : {
        "modelref" : true,
        "id" : "RAWSQLCALL1"
      }
    }, {
      "getDstPSDELogicNode" : {
        "modelref" : true,
        "id" : "PREPAREPARAM6"
      },
      "name" : "合计已登记工时为0",
      "getPSDELogicLinkGroupCond" : {
        "groupOP" : "AND",
        "logicType" : "GROUP",
        "name" : "连接条件组",
        "getPSDELogicLinkConds" : [ {
          "condOP" : "EQ",
          "dstFieldName" : "DATETIME_VALUE",
          "getDstLogicParam" : {
            "modelref" : true,
            "id" : "actual"
          },
          "logicType" : "SINGLE",
          "name" : "actual[DATETIME_VALUE] 等于(=) 0",
          "paramValue" : "0"
        } ]
      },
      "getSrcPSDELogicNode" : {
        "modelref" : true,
        "id" : "RAWSQLCALL1"
      }
    } ],
    "getPSDELogicNodeParams" : [ {
      "name" : "actual[OWNER_ID]",
      "paramAction" : "SQLPARAM",
      "srcFieldName" : "OWNER_ID",
      "getSrcPSDELogicParam" : {
        "modelref" : true,
        "id" : "actual"
      },
      "srcValueType" : "SRCDLPARAM"
    }, {
      "name" : "actual[OWNER_TYPE]",
      "paramAction" : "SQLPARAM",
      "srcFieldName" : "OWNER_TYPE",
      "getSrcPSDELogicParam" : {
        "modelref" : true,
        "id" : "actual"
      },
      "srcValueType" : "SRCDLPARAM"
    }, {
      "name" : "actual[NAME]",
      "paramAction" : "SQLPARAM",
      "srcFieldName" : "NAME",
      "getSrcPSDELogicParam" : {
        "modelref" : true,
        "id" : "actual"
      },
      "srcValueType" : "SRCDLPARAM"
    } ],
    "sql" : "select sum(DURATION) as `DECIMAL_VALUE` from `workload` where PRINCIPAL_ID = ? and PRINCIPAL_TYPE = ? and CATEGORY = ?",
    "topPos" : 920,
    "fillDstLogicParam" : true
  }, {
    "codeName" : "DEACTION7",
    "getDstPSDEAction" : {
      "modelref" : true,
      "path" : "PSMODULES/Base/PSDATAENTITIES/extend_storage/PSDEACTIONS/Save.json"
    },
    "getDstPSDELogicParam" : {
      "modelref" : true,
      "id" : "actual"
    },
    "getDstPSDataEntity" : {
      "modelref" : true,
      "path" : "PSMODULES/Base/PSDATAENTITIES/extend_storage.json"
    },
    "leftPos" : 160,
    "logicNodeType" : "DEACTION",
    "name" : "更新实际工时",
    "getPSDELogicLinks" : [ {
      "getDstPSDELogicNode" : {
        "modelref" : true,
        "id" : "PREPAREPARAM7"
      },
      "name" : "存在父工作项",
      "getPSDELogicLinkGroupCond" : {
        "groupOP" : "AND",
        "logicType" : "GROUP",
        "name" : "连接条件组",
        "getPSDELogicLinkConds" : [ {
          "condOP" : "ISNOTNULL",
          "dstFieldName" : "PID",
          "getDstLogicParam" : {
            "modelref" : true,
            "id" : "work_item"
          },
          "logicType" : "SINGLE",
          "name" : "work_item[PID] 值不为空(NotNil)"
        } ]
      },
      "getSrcPSDELogicNode" : {
        "modelref" : true,
        "id" : "DEACTION7"
      }
    } ],
    "getRetPSDELogicParam" : {
      "modelref" : true,
      "id" : "actual"
    },
    "topPos" : 1150
  }, {
    "codeName" : "PREPAREPARAM7",
    "leftPos" : 160,
    "logicNodeType" : "PREPAREPARAM",
    "name" : "填充父工作项标识",
    "getPSDELogicLinks" : [ {
      "getDstPSDELogicNode" : {
        "modelref" : true,
        "id" : "DELOGIC1"
      },
      "name" : "连接名称",
      "getSrcPSDELogicNode" : {
        "modelref" : true,
        "id" : "PREPAREPARAM7"
      }
    } ],
    "getPSDELogicNodeParams" : [ {
      "dstFieldName" : "PRINCIPAL_ID",
      "getDstPSDELogicParam" : {
        "modelref" : true,
        "id" : "u_workload"
      },
      "name" : "work_item[PID] ==> u_workload[PRINCIPAL_ID]",
      "paramAction" : "SETPARAMVALUE",
      "srcFieldName" : "PID",
      "getSrcPSDELogicParam" : {
        "modelref" : true,
        "id" : "work_item"
      },
      "srcValueType" : "SRCDLPARAM"
    } ],
    "topPos" : 1371
  }, {
    "codeName" : "DELOGIC1",
    "getDstPSDELogic" : {
      "modelref" : true,
      "path" : "PSMODULES/Base/PSDATAENTITIES/workload/PSDELOGICS/workload_auto_cal.json"
    },
    "getDstPSDELogicParam" : {
      "modelref" : true,
      "id" : "u_workload"
    },
    "getDstPSDataEntity" : {
      "modelref" : true,
      "path" : "PSMODULES/Base/PSDATAENTITIES/workload.json"
    },
    "leftPos" : 160,
    "logicNodeType" : "DELOGIC",
    "name" : "自动计算父工时",
    "topPos" : 1519
  } ],
  "getPSDELogicParams" : [ {
    "codeName" : "Default",
    "logicName" : "传入变量",
    "name" : "传入变量",
    "getParamPSDataEntity" : {
      "modelref" : true,
      "path" : "PSMODULES/Base/PSDATAENTITIES/workload.json"
    },
    "default" : true,
    "entityParam" : true
  }, {
    "codeName" : "actual",
    "logicName" : "实际工时",
    "name" : "实际工时",
    "getParamPSDataEntity" : {
      "modelref" : true,
      "path" : "PSMODULES/Base/PSDATAENTITIES/extend_storage.json"
    },
    "entityParam" : true
  }, {
    "codeName" : "idea",
    "logicName" : "产品需求",
    "name" : "产品需求",
    "getParamPSDataEntity" : {
      "modelref" : true,
      "path" : "PSMODULES/ProdMgmt/PSDATAENTITIES/idea.json"
    },
    "entityParam" : true
  }, {
    "codeName" : "remaining",
    "logicName" : "剩余工时",
    "name" : "剩余工时",
    "getParamPSDataEntity" : {
      "modelref" : true,
      "path" : "PSMODULES/Base/PSDATAENTITIES/extend_storage.json"
    },
    "entityParam" : true
  }, {
    "codeName" : "test_case",
    "logicName" : "测试用例",
    "name" : "测试用例",
    "getParamPSDataEntity" : {
      "modelref" : true,
      "path" : "PSMODULES/TestMgmt/PSDATAENTITIES/test_case.json"
    },
    "entityParam" : true
  }, {
    "codeName" : "u_workload",
    "logicName" : "是否更新工时",
    "name" : "是否更新工时",
    "getParamPSDataEntity" : {
      "modelref" : true,
      "path" : "PSMODULES/Base/PSDATAENTITIES/workload.json"
    },
    "entityParam" : true
  }, {
    "codeName" : "work_item",
    "logicName" : "工作项",
    "name" : "工作项",
    "getParamPSDataEntity" : {
      "modelref" : true,
      "path" : "PSMODULES/ProjMgmt/PSDATAENTITIES/work_item.json"
    },
    "entityParam" : true
  } ],
  "getStartPSDELogicNode" : {
    "modelref" : true,
    "id" : "Begin"
  },
  "enableBackend" : true,
  "enableFront" : false
}