{
  "actionHolder" : 1,
  "actionMode" : "CUSTOM",
  "actionType" : "DELOGIC",
  "codeName" : "copy_page",
  "dataAccessAction" : "READ",
  "dynaModelFilePath" : "PSMODULES/Wiki/PSDATAENTITIES/article_page/PSDEACTIONS/copy_page.json",
  "logicName" : "复制页面",
  "name" : "copy_page",
  "getPSDEActionInput" : {
    "name" : "Copy_pageInput",
    "getPSDEMethodDTO" : {
      "modelref" : true,
      "id" : "article_page_dto"
    },
    "type" : "DTO"
  },
  "getPSDEActionReturn" : {
    "name" : "Copy_pageResult",
    "type" : "VOID"
  },
  "getPSDELogic" : {
    "modelref" : true,
    "path" : "PSMODULES/Wiki/PSDATAENTITIES/article_page/PSDELOGICS/copy_page.json"
  },
  "enableFront" : false
}