{
  "accUserMode" : 2,
  "caption" : "全部计划",
  "codeName" : "product_plan_all_grid_view",
  "dynaModelFilePath" : "PSSYSAPPS/plmweb/PSAPPDEVIEWS/product_plan_all_grid_view.json",
  "gridRowActiveMode" : 1,
  "name" : "product_planall_grid_view",
  "getPSAppDataEntity" : {
    "modelref" : true,
    "path" : "PSSYSAPPS/plmweb/PSAPPDATAENTITIES/product_plan.json"
  },
  "getPSAppModule" : {
    "modelref" : true,
    "path" : "PSSYSAPPS/plmweb/PSAPPMODULES/ProdMgmt.json"
  },
  "getPSAppViewEngines" : [ {
    "engineCat" : "VIEW",
    "engineType" : "GridView",
    "name" : "engine"
  } ],
  "getPSAppViewLogics" : [ {
    "logicTrigger" : "CUSTOM",
    "logicType" : "APPUILOGIC",
    "name" : "newdata",
    "getPSAppUILogic" : {
      "actionAfterWizard" : "DEFAULT",
      "logicType" : "PREDEFINED",
      "name" : "新建数据",
      "getNewDataPSAppView" : {
        "openMode" : "POPUPMODAL",
        "getRefPSAppView" : {
          "modelref" : true,
          "path" : "PSSYSAPPS/plmweb/PSAPPDEVIEWS/product_plan_quick_create_view.json",
          "viewType" : "DEOPTVIEW"
        }
      },
      "getPSAppUILogicRefViews" : [ {
        "openMode" : "POPUPMODAL",
        "getRefPSAppView" : {
          "modelref" : true,
          "path" : "PSSYSAPPS/plmweb/PSAPPDEVIEWS/product_plan_quick_create_view.json",
          "viewType" : "DEOPTVIEW"
        }
      } ],
      "viewLogicType" : "APP_NEWDATA",
      "batchAddOnly" : false,
      "enableBatchAdd" : false,
      "enableWizardAdd" : false
    }
  }, {
    "logicTrigger" : "CUSTOM",
    "logicType" : "APPUILOGIC",
    "name" : "opendata",
    "getPSAppUILogic" : {
      "logicType" : "PREDEFINED",
      "name" : "打开数据",
      "getOpenDataPSAppView" : {
        "openMode" : "POPUPMODAL",
        "getRefPSAppView" : {
          "modelref" : true,
          "path" : "PSSYSAPPS/plmweb/PSAPPDEVIEWS/idea_plan_count_grid_view.json",
          "viewType" : "DEGRIDVIEW"
        }
      },
      "getPSAppUILogicRefViews" : [ {
        "openMode" : "POPUPMODAL",
        "getRefPSAppView" : {
          "modelref" : true,
          "path" : "PSSYSAPPS/plmweb/PSAPPDEVIEWS/idea_plan_count_grid_view.json",
          "viewType" : "DEGRIDVIEW"
        }
      } ],
      "viewLogicType" : "APP_OPENDATA",
      "editMode" : true
    }
  } ],
  "getPSAppViewNavParams" : [ {
    "key" : "product",
    "name" : "product",
    "value" : "product",
    "rawValue" : false
  } ],
  "getPSAppViewRefs" : [ {
    "name" : "EDITDATA",
    "openMode" : "POPUPMODAL",
    "realOpenMode" : "POPUPMODAL",
    "realTitle" : "计划内容",
    "getRealTitlePSLanguageRes" : {
      "lanResTag" : "PAGE.TITLE.IDEA.MAIN_VIEW_PLAN"
    },
    "getRefPSAppView" : {
      "modelref" : true,
      "path" : "PSSYSAPPS/plmweb/PSAPPDEVIEWS/idea_plan_count_grid_view.json",
      "viewType" : "DEGRIDVIEW"
    }
  }, {
    "name" : "NEWDATA",
    "realOpenMode" : "POPUPMODAL",
    "realTitle" : "新建计划",
    "getRefPSAppView" : {
      "modelref" : true,
      "path" : "PSSYSAPPS/plmweb/PSAPPDEVIEWS/product_plan_quick_create_view.json",
      "viewType" : "DEOPTVIEW"
    }
  }, {
    "name" : "OPENDATA",
    "realTitle" : "计划内容",
    "getRealTitlePSLanguageRes" : {
      "lanResTag" : "PAGE.TITLE.IDEA.MAIN_VIEW_PLAN"
    },
    "getRefPSAppView" : {
      "modelref" : true,
      "path" : "PSSYSAPPS/plmweb/PSAPPDEVIEWS/idea_plan_count_grid_view.json",
      "viewType" : "DEGRIDVIEW"
    }
  } ],
  "getPSControls" : [ {
    "codeName" : "all_grid_view_toolbar",
    "controlType" : "TOOLBAR",
    "logicName" : "新建计划",
    "name" : "toolbar",
    "getPSAppDataEntity" : {
      "modelref" : true,
      "path" : "PSSYSAPPS/plmweb/PSAPPDATAENTITIES/product_plan.json"
    },
    "getPSControlParam" : {
      "id" : "TOOLBAR"
    },
    "getPSDEToolbarItems" : [ {
      "getCapPSLanguageRes" : {
        "lanResTag" : "TBB.TEXT.*.NEW"
      },
      "caption" : "新建计划",
      "groupExtractMode" : "ITEM",
      "itemType" : "DEUIACTION",
      "name" : "deuiaction1",
      "noPrivDisplayMode" : 2,
      "getPSAppViewUIAction" : {
        "modelref" : true,
        "id" : "toolbar_deuiaction1"
      },
      "getPSSysImage" : {
        "glyph" : "xf067@FontAwesome",
        "cssClass" : "fa fa-plus"
      },
      "getPSUIAction" : {
        "getCapPSLanguageRes" : {
          "lanResTag" : "TBB.TEXT.*.NEW"
        },
        "caption" : "新建",
        "codeName" : "New",
        "fullCodeName" : "New",
        "name" : "表格界面_新建操作",
        "getPSSysImage" : {
          "glyph" : "xf0f6@FontAwesome",
          "cssClass" : "fa fa-file-text-o"
        },
        "predefinedType" : "GRIDVIEW_NEWACTION",
        "timeout" : 60000,
        "getTooltipPSLanguageRes" : {
          "lanResTag" : "TBB.TOOLTIP.*.NEW"
        },
        "uIActionMode" : "SYS",
        "uIActionTag" : "New",
        "uIActionType" : "DEUIACTION"
      },
      "tooltip" : "新建计划",
      "getTooltipPSLanguageRes" : {
        "lanResTag" : "TBB.TOOLTIP.*.NEW"
      },
      "showCaption" : true,
      "showIcon" : true
    } ],
    "xDataControlName" : "grid",
    "modelid" : "3faaa365ca4fe84f02726191b010e4fb",
    "modeltype" : "PSDETOOLBAR"
  }, {
    "aggMode" : "NONE",
    "codeName" : "main",
    "columnEnableFilter" : 2,
    "columnEnableLink" : 2,
    "controlType" : "GRID",
    "getCreatePSControlAction" : {
      "actionName" : "Create",
      "actionType" : "DEACTION",
      "dataAccessAction" : "CREATE",
      "name" : "create",
      "getPSAppDEMethod" : {
        "modelref" : true,
        "id" : "create"
      },
      "getPSAppDataEntity" : {
        "modelref" : true,
        "path" : "PSSYSAPPS/plmweb/PSAPPDATAENTITIES/product_plan.json"
      }
    },
    "dynaModelFilePath" : "PSSYSAPPS/plmweb/PSAPPDATAENTITIES/product_plan/PSGRIDS/main.json",
    "getFetchPSControlAction" : {
      "modelref" : true,
      "id" : "fetch",
      "actionType" : "DEDATASET",
      "name" : "fetch",
      "getPSAppDEMethod" : {
        "modelref" : true,
        "id" : "fetch_normal"
      },
      "getPSAppDataEntity" : {
        "modelref" : true,
        "path" : "PSSYSAPPS/plmweb/PSAPPDATAENTITIES/product_plan.json"
      }
    },
    "getGetDraftPSControlAction" : {
      "actionName" : "GetDraft",
      "actionType" : "DEACTION",
      "dataAccessAction" : "CREATE",
      "name" : "loaddraft",
      "getPSAppDEMethod" : {
        "modelref" : true,
        "id" : "get_draft"
      },
      "getPSAppDataEntity" : {
        "modelref" : true,
        "path" : "PSSYSAPPS/plmweb/PSAPPDATAENTITIES/product_plan.json"
      }
    },
    "getGetPSControlAction" : {
      "actionName" : "Get",
      "actionType" : "DEACTION",
      "dataAccessAction" : "READ",
      "name" : "load",
      "getPSAppDEMethod" : {
        "modelref" : true,
        "id" : "get"
      },
      "getPSAppDataEntity" : {
        "modelref" : true,
        "path" : "PSSYSAPPS/plmweb/PSAPPDATAENTITIES/product_plan.json"
      }
    },
    "groupMode" : "NONE",
    "logicName" : "主表格",
    "getPSAppDataEntity" : {
      "modelref" : true,
      "path" : "PSSYSAPPS/plmweb/PSAPPDATAENTITIES/product_plan.json"
    },
    "getPSControlHandler" : {
      "getPSHandlerActions" : [ {
        "actionName" : "Get",
        "actionType" : "DEACTION",
        "dataAccessAction" : "READ",
        "name" : "load",
        "getPSAppDEMethod" : {
          "modelref" : true,
          "id" : "get"
        },
        "getPSAppDataEntity" : {
          "modelref" : true,
          "path" : "PSSYSAPPS/plmweb/PSAPPDATAENTITIES/product_plan.json"
        }
      }, {
        "actionName" : "Create",
        "actionType" : "DEACTION",
        "dataAccessAction" : "CREATE",
        "name" : "create",
        "getPSAppDEMethod" : {
          "modelref" : true,
          "id" : "create"
        },
        "getPSAppDataEntity" : {
          "modelref" : true,
          "path" : "PSSYSAPPS/plmweb/PSAPPDATAENTITIES/product_plan.json"
        }
      }, {
        "actionName" : "Update",
        "actionType" : "DEACTION",
        "dataAccessAction" : "UPDATE",
        "name" : "update",
        "getPSAppDEMethod" : {
          "modelref" : true,
          "id" : "update"
        },
        "getPSAppDataEntity" : {
          "modelref" : true,
          "path" : "PSSYSAPPS/plmweb/PSAPPDATAENTITIES/product_plan.json"
        }
      }, {
        "actionName" : "Remove",
        "actionType" : "DEACTION",
        "dataAccessAction" : "DELETE",
        "name" : "remove",
        "getPSAppDEMethod" : {
          "modelref" : true,
          "id" : "remove"
        },
        "getPSAppDataEntity" : {
          "modelref" : true,
          "path" : "PSSYSAPPS/plmweb/PSAPPDATAENTITIES/product_plan.json"
        }
      }, {
        "actionName" : "GetDraft",
        "actionType" : "DEACTION",
        "dataAccessAction" : "CREATE",
        "name" : "loaddraft",
        "getPSAppDEMethod" : {
          "modelref" : true,
          "id" : "get_draft"
        },
        "getPSAppDataEntity" : {
          "modelref" : true,
          "path" : "PSSYSAPPS/plmweb/PSAPPDATAENTITIES/product_plan.json"
        }
      }, {
        "actionType" : "DEDATASET",
        "name" : "fetch",
        "getPSAppDEMethod" : {
          "modelref" : true,
          "id" : "fetch_normal"
        },
        "getPSAppDataEntity" : {
          "modelref" : true,
          "path" : "PSSYSAPPS/plmweb/PSAPPDATAENTITIES/product_plan.json"
        }
      } ],
      "userDRAction" : "READ",
      "enableDEFieldPrivilege" : false,
      "id" : "数据表格处理器"
    },
    "getPSControlParam" : {
      "autoLoad" : true,
      "showBusyIndicator" : true,
      "id" : "GRID"
    },
    "getPSDEGridColumns" : [ {
      "align" : "LEFT",
      "cLConvertMode" : "NONE",
      "getCapPSLanguageRes" : {
        "lanResTag" : "DEF.LNAME.NAME"
      },
      "caption" : "计划名称",
      "codeName" : "name",
      "columnType" : "DEFGRIDCOLUMN",
      "dataItemName" : "name",
      "excelCaption" : "计划名称",
      "name" : "name",
      "noPrivDisplayMode" : 1,
      "getPSAppDEField" : {
        "name" : "NAME",
        "codeName" : "name"
      },
      "getPSDEUIActionGroup" : {
        "codeName" : "Usr1228161361",
        "name" : "计划表格操作项",
        "getPSAppDataEntity" : {
          "modelref" : true,
          "path" : "PSSYSAPPS/plmweb/PSAPPDATAENTITIES/product_plan.json"
        },
        "getPSUIActionGroupDetails" : [ {
          "caption" : "编辑",
          "detailType" : "DEUIACTION",
          "name" : "uc47afc7",
          "getPSSysImage" : {
            "glyph" : "xf044@FontAwesome",
            "cssClass" : "fa fa-edit"
          },
          "getPSUIAction" : {
            "actionTarget" : "SINGLEKEY",
            "caption" : "编辑",
            "codeName" : "edit_plan",
            "getFrontPSAppView" : {
              "modelref" : true,
              "path" : "PSSYSAPPS/plmweb/PSAPPDEVIEWS/product_plan_edit_option_view.json",
              "viewType" : "DEOPTVIEW"
            },
            "frontProcessType" : "WIZARD",
            "fullCodeName" : "product_plan_edit_plan",
            "name" : "编辑",
            "getPSAppDataEntity" : {
              "modelref" : true,
              "path" : "PSSYSAPPS/plmweb/PSAPPDATAENTITIES/product_plan.json"
            },
            "getPSSysImage" : {
              "glyph" : "xf044@FontAwesome",
              "cssClass" : "fa fa-edit"
            },
            "timeout" : 60000,
            "uIActionMode" : "FRONT",
            "uIActionTag" : "edit_plan",
            "uIActionType" : "DEUIACTION",
            "id" : "edit_plan@product_plan"
          },
          "addSeparator" : false,
          "showCaption" : true,
          "showIcon" : true
        }, {
          "caption" : "删除",
          "detailType" : "DEUIACTION",
          "name" : "u7841db0",
          "getPSSysImage" : {
            "glyph" : "xf014@FontAwesome",
            "cssClass" : "fa fa-trash-o"
          },
          "getPSUIAction" : {
            "actionTarget" : "SINGLEKEY",
            "caption" : "删除",
            "codeName" : "delete",
            "confirmMsg" : "确认删除该计划？",
            "fullCodeName" : "product_plan_delete",
            "name" : "删除",
            "getPSAppDEMethod" : {
              "modelref" : true,
              "id" : "delete"
            },
            "getPSAppDataEntity" : {
              "modelref" : true,
              "path" : "PSSYSAPPS/plmweb/PSAPPDATAENTITIES/product_plan.json"
            },
            "getPSSysImage" : {
              "glyph" : "xf014@FontAwesome",
              "cssClass" : "fa fa-trash-o"
            },
            "refreshMode" : 1,
            "successMsg" : "删除成功",
            "timeout" : 60000,
            "uIActionMode" : "BACKEND",
            "uIActionTag" : "delete",
            "uIActionType" : "DEUIACTION",
            "enableConfirm" : true,
            "reloadData" : true,
            "id" : "delete@product_plan"
          },
          "addSeparator" : false,
          "showCaption" : true,
          "showIcon" : true
        } ],
        "uniqueTag" : "product_plan__Usr1228161361"
      },
      "width" : 300,
      "widthUnit" : "STAR",
      "enableSort" : true
    }, {
      "align" : "LEFT",
      "cLConvertMode" : "FRONT",
      "caption" : "类别",
      "codeName" : "categorys",
      "columnType" : "DEFGRIDCOLUMN",
      "dataItemName" : "categories",
      "excelCaption" : "类别",
      "name" : "categorys",
      "noPrivDisplayMode" : 1,
      "getPSAppCodeList" : {
        "modelref" : true,
        "path" : "PSSYSAPPS/plmweb/PSAPPCODELISTS/ProdMgmt__category.json"
      },
      "getPSAppDEField" : {
        "name" : "CATEGORIES",
        "codeName" : "categories"
      },
      "width" : 200,
      "widthUnit" : "PX",
      "enableRowEdit" : true,
      "enableSort" : true
    }, {
      "align" : "LEFT",
      "cLConvertMode" : "NONE",
      "caption" : "计划开始",
      "codeName" : "start_at",
      "columnType" : "DEFGRIDCOLUMN",
      "dataItemName" : "start_at",
      "excelCaption" : "计划开始",
      "name" : "start_at",
      "noPrivDisplayMode" : 1,
      "getPSAppDEField" : {
        "name" : "START_AT",
        "codeName" : "start_at"
      },
      "valueFormat" : "YYYY-MM-DD",
      "width" : 200,
      "widthUnit" : "PX",
      "enableSort" : true
    }, {
      "align" : "LEFT",
      "cLConvertMode" : "NONE",
      "caption" : "计划结束",
      "codeName" : "end_at",
      "columnType" : "DEFGRIDCOLUMN",
      "dataItemName" : "end_at",
      "excelCaption" : "计划结束",
      "name" : "end_at",
      "noPrivDisplayMode" : 1,
      "getPSAppDEField" : {
        "name" : "END_AT",
        "codeName" : "end_at"
      },
      "valueFormat" : "YYYY-MM-DD",
      "width" : 200,
      "widthUnit" : "PX",
      "enableSort" : true
    }, {
      "align" : "LEFT",
      "cLConvertMode" : "NONE",
      "caption" : "负责人",
      "codeName" : "assignee_name",
      "columnType" : "DEFGRIDCOLUMN",
      "dataItemName" : "assignee_name",
      "excelCaption" : "负责人",
      "name" : "assignee_name",
      "noPrivDisplayMode" : 1,
      "getPSAppDEField" : {
        "name" : "ASSIGNEE_NAME",
        "codeName" : "assignee_name"
      },
      "width" : 200,
      "widthUnit" : "PX",
      "enableRowEdit" : true,
      "enableSort" : true
    } ],
    "getPSDEGridDataItems" : [ {
      "dataType" : 25,
      "name" : "name",
      "getPSAppDEField" : {
        "name" : "NAME",
        "codeName" : "name"
      }
    }, {
      "dataType" : 25,
      "name" : "categories",
      "getPSAppDEField" : {
        "name" : "CATEGORIES",
        "codeName" : "categories"
      }
    }, {
      "format" : "YYYY-MM-DD",
      "dataType" : 5,
      "name" : "start_at",
      "getPSAppDEField" : {
        "name" : "START_AT",
        "codeName" : "start_at"
      }
    }, {
      "format" : "YYYY-MM-DD",
      "dataType" : 5,
      "name" : "end_at",
      "getPSAppDEField" : {
        "name" : "END_AT",
        "codeName" : "end_at"
      }
    }, {
      "dataType" : 25,
      "name" : "assignee_name",
      "getPSAppDEField" : {
        "name" : "ASSIGNEE_NAME",
        "codeName" : "assignee_name"
      }
    }, {
      "dataType" : 25,
      "name" : "srfkey",
      "getPSAppDEField" : {
        "name" : "ID",
        "codeName" : "id"
      }
    }, {
      "dataType" : 25,
      "name" : "srfdataaccaction",
      "getPSAppDEField" : {
        "name" : "ID",
        "codeName" : "id"
      },
      "dataAccessAction" : true
    }, {
      "dataType" : 25,
      "name" : "product_id",
      "getPSAppDEField" : {
        "name" : "PRODUCT_ID",
        "codeName" : "product_id"
      }
    }, {
      "dataType" : 25,
      "name" : "srfmajortext",
      "getPSAppDEField" : {
        "name" : "NAME",
        "codeName" : "name"
      }
    } ],
    "getPSDEGridEditItems" : [ {
      "caption" : "类别",
      "codeName" : "categorys",
      "enableCond" : 3,
      "ignoreInput" : 0,
      "name" : "categorys",
      "getPSAppDEField" : {
        "name" : "CATEGORIES",
        "codeName" : "categories"
      },
      "getPSEditor" : {
        "editorParams" : {
          "readonly" : "true"
        },
        "editorType" : "MDROPDOWNLIST",
        "name" : "categorys",
        "getPSAppCodeList" : {
          "modelref" : true,
          "path" : "PSSYSAPPS/plmweb/PSAPPCODELISTS/ProdMgmt__category.json"
        },
        "readOnly" : true,
        "singleSelect" : false
      },
      "allowEmpty" : true,
      "needCodeListConfig" : true
    }, {
      "caption" : "负责人",
      "codeName" : "assignee_name",
      "enableCond" : 3,
      "ignoreInput" : 0,
      "name" : "assignee_name",
      "getPSAppDEField" : {
        "name" : "ASSIGNEE_NAME",
        "codeName" : "assignee_name"
      },
      "getPSEditor" : {
        "editorParams" : {
          "SRFNAVPARAM.n_department_id_eq" : "%srforgsectorid%",
          "AC" : "TRUE",
          "readonly" : "true",
          "TRIGGER" : "TRUE",
          "SRFNAVCTX.product" : "%product%",
          "URL" : "product_members/fetchdefault",
          "PICKUPVIEW" : "FALSE",
          "USERMETHOD" : "post",
          "SRFNAVPARAM.n_product_id_eq" : "%product%",
          "USERMAP" : "{\"id\":\"user_id\",\"name\":\"name\"}",
          "DEPTMETHOD" : "get",
          "DEPTMAP" : "{\"id\":\"id\",\"name\":\"display_name\"}",
          "DEPTURL" : "/users/fetchdefault"
        },
        "editorStyle" : "PERSONEL_SELECT",
        "editorType" : "PICKEREX_TRIGGER",
        "handlerType" : "PickupText",
        "name" : "assignee_name",
        "getPSNavigateContexts" : [ {
          "key" : "PRODUCT",
          "name" : "PRODUCT",
          "value" : "product",
          "rawValue" : false
        } ],
        "getPSNavigateParams" : [ {
          "key" : "n_department_id_eq",
          "name" : "n_department_id_eq",
          "value" : "srforgsectorid",
          "rawValue" : false
        }, {
          "key" : "n_product_id_eq",
          "name" : "n_product_id_eq",
          "value" : "product",
          "rawValue" : false
        } ],
        "getPSSysPFPlugin" : {
          "pluginType" : "EDITOR_CUSTOMSTYLE",
          "pluginCode" : "PERSON_SELECT",
          "runtimeObject" : true
        },
        "enableAC" : true,
        "enablePickupView" : false,
        "forceSelection" : true,
        "readOnly" : true,
        "showTrigger" : true,
        "singleSelect" : true
      },
      "allowEmpty" : true
    }, {
      "caption" : "标识",
      "codeName" : "srfkey",
      "enableCond" : 3,
      "ignoreInput" : 0,
      "name" : "srfkey",
      "getPSAppDEField" : {
        "name" : "ID",
        "codeName" : "id"
      },
      "getPSEditor" : {
        "editorType" : "HIDDEN",
        "name" : "srfkey"
      },
      "allowEmpty" : true
    } ],
    "pagingSize" : 20,
    "getRemovePSControlAction" : {
      "actionName" : "Remove",
      "actionType" : "DEACTION",
      "dataAccessAction" : "DELETE",
      "name" : "remove",
      "getPSAppDEMethod" : {
        "modelref" : true,
        "id" : "remove"
      },
      "getPSAppDataEntity" : {
        "modelref" : true,
        "path" : "PSSYSAPPS/plmweb/PSAPPDATAENTITIES/product_plan.json"
      }
    },
    "sortMode" : "REMOTE",
    "getUpdatePSControlAction" : {
      "actionName" : "Update",
      "actionType" : "DEACTION",
      "dataAccessAction" : "UPDATE",
      "name" : "update",
      "getPSAppDEMethod" : {
        "modelref" : true,
        "id" : "update"
      },
      "getPSAppDataEntity" : {
        "modelref" : true,
        "path" : "PSSYSAPPS/plmweb/PSAPPDATAENTITIES/product_plan.json"
      }
    },
    "hasWFDataItems" : false,
    "enableColFilter" : false,
    "enableCustomized" : true,
    "enableGroup" : false,
    "enablePagingBar" : true,
    "enableRowEdit" : true,
    "enableRowEditOrder" : false,
    "enableRowNew" : true,
    "forceFit" : false,
    "hideHeader" : false,
    "noSort" : false,
    "singleSelect" : true,
    "name" : "grid",
    "modelid" : "1bbf5a31a418af2094e26e0625832e3a",
    "modeltype" : "PSDEGRID"
  }, {
    "codeName" : "default",
    "controlType" : "SEARCHFORM",
    "defaultLabelWidth" : 130,
    "dynaModelFilePath" : "PSSYSAPPS/plmweb/PSAPPDATAENTITIES/product_plan/PSSEARCHFORMS/default.json",
    "logicName" : "默认搜索表单",
    "getPSAppDataEntity" : {
      "modelref" : true,
      "path" : "PSSYSAPPS/plmweb/PSAPPDATAENTITIES/product_plan.json"
    },
    "getPSControlHandler" : {
      "getPSHandlerActions" : [ {
        "actionType" : "FILTERACTION",
        "name" : "load",
        "getPSAppDEMethod" : {
          "modelref" : true,
          "id" : "FilterGet"
        },
        "getPSAppDataEntity" : {
          "modelref" : true,
          "path" : "PSSYSAPPS/plmweb/PSAPPDATAENTITIES/product_plan.json"
        }
      }, {
        "actionType" : "FILTERACTION",
        "name" : "loaddraft",
        "getPSAppDEMethod" : {
          "modelref" : true,
          "id" : "FilterGetDraft"
        },
        "getPSAppDataEntity" : {
          "modelref" : true,
          "path" : "PSSYSAPPS/plmweb/PSAPPDATAENTITIES/product_plan.json"
        }
      }, {
        "actionType" : "FILTERACTION",
        "name" : "search",
        "getPSAppDEMethod" : {
          "modelref" : true,
          "id" : "FilterSearch"
        },
        "getPSAppDataEntity" : {
          "modelref" : true,
          "path" : "PSSYSAPPS/plmweb/PSAPPDATAENTITIES/product_plan.json"
        }
      } ],
      "enableDEFieldPrivilege" : false,
      "id" : "搜索表单处理器"
    },
    "getPSControlParam" : {
      "autoLoad" : true,
      "showBusyIndicator" : true,
      "id" : "SEARCHFORM"
    },
    "getPSDEFormPages" : [ {
      "caption" : "常规条件",
      "codeName" : "formpage1",
      "detailStyle" : "DEFAULT",
      "detailType" : "FORMPAGE",
      "name" : "formpage1",
      "getPSLayout" : {
        "childColLG" : -1,
        "childColMD" : 24,
        "childColSM" : -1,
        "childColXS" : -1,
        "columnCount" : 24,
        "layout" : "TABLE_24COL"
      },
      "infoGroupMode" : false
    } ],
    "getPSLayout" : {
      "childColLG" : -1,
      "childColMD" : 24,
      "childColSM" : -1,
      "childColXS" : -1,
      "columnCount" : 24,
      "layout" : "TABLE_24COL"
    },
    "searchButtonStyle" : "DEFAULT",
    "tabHeaderPos" : "TOP",
    "enableAdvanceSearch" : false,
    "enableAutoSearch" : false,
    "enableFilterSave" : false,
    "noTabHeader" : true,
    "name" : "searchform",
    "modelid" : "0fd69492a6bad480f45a8da8f90fb085",
    "modeltype" : "PSDEFORM_SEARCHFORM"
  }, {
    "controlType" : "SEARCHBAR",
    "name" : "searchbar",
    "getPSAppDataEntity" : {
      "modelref" : true,
      "path" : "PSSYSAPPS/plmweb/PSAPPDATAENTITIES/product_plan.json"
    },
    "getPSControlParam" : {
      "id" : "searchbar"
    },
    "quickGroupCount" : -1,
    "quickSearchMode" : 1,
    "quickSearchWidth" : 0,
    "enableFilter" : false,
    "enableGroup" : false,
    "enableQuickSearch" : true,
    "mobileSearchBar" : false
  }, {
    "caption" : "全部计划",
    "codeName" : "all_grid_view_captionbar",
    "controlType" : "CAPTIONBAR",
    "name" : "captionbar",
    "getPSAppDataEntity" : {
      "modelref" : true,
      "path" : "PSSYSAPPS/plmweb/PSAPPDATAENTITIES/product_plan.json"
    },
    "getPSControlParam" : { }
  } ],
  "getPSDEViewCodeName" : "all_grid_view",
  "getPSDEViewId" : "a225eb6e6a06ff36dd5e39c22a02a0d2",
  "getPSViewLayoutPanel" : {
    "codeName" : "layoutpanel",
    "controlStyle" : "APPDEGRIDVIEW",
    "controlType" : "VIEWLAYOUTPANEL",
    "name" : "layoutpanel",
    "getPSAppDataEntity" : {
      "modelref" : true,
      "path" : "PSSYSAPPS/plmweb/PSAPPDATAENTITIES/product_plan.json"
    },
    "getPSControlParam" : { },
    "layoutBodyOnly" : true,
    "layoutPanel" : true,
    "useDefaultLayout" : true
  },
  "title" : "全部计划",
  "viewStyle" : "DEFAULT",
  "viewType" : "DEGRIDVIEW",
  "xDataControlName" : "grid",
  "enableDP" : true,
  "enableExport" : true,
  "enableFilter" : true,
  "enableImport" : true,
  "enableQuickSearch" : true,
  "enableRowEdit" : true,
  "enableSearch" : true,
  "rowEditDefault" : false,
  "modelid" : "539a5c7d309db9118489a32e62ccbd9e",
  "modeltype" : "PSAPPDEVIEW",
  "getPSAppDERSPaths" : [ [ {
    "actionRSMode" : 1,
    "codeName" : "plans",
    "dataRSMode" : 0,
    "majorDECodeName" : "product",
    "majorDEName" : "PRODUCT",
    "getMajorPSAppDataEntity" : {
      "modelref" : true,
      "path" : "PSSYSAPPS/plmweb/PSAPPDATAENTITIES/product.json"
    },
    "minorDECodeName" : "product_plan",
    "minorDEName" : "PRODUCT_PLAN",
    "getMinorPSAppDataEntity" : {
      "modelref" : true,
      "path" : "PSSYSAPPS/plmweb/PSAPPDATAENTITIES/product_plan.json"
    },
    "name" : "DER1N_PLAN_PRODUCT_PRODUCT_ID",
    "getParentPSAppDEField" : {
      "name" : "PRODUCT_ID",
      "codeName" : "product_id"
    },
    "rSMode" : 2
  } ] ]
}