{
  "accUserMode" : 2,
  "getCapPSLanguageRes" : {
    "lanResTag" : "DE.LNAME.PSCOREPRDFUNC"
  },
  "caption" : "核心产品功能",
  "codeName" : "ps_core_prd_func_modeling_ide_html_view",
  "dynaModelFilePath" : "PSSYSAPPS/plmweb/PSAPPDEVIEWS/ps_core_prd_func_modeling_ide_html_view.json",
  "htmlUrl" : "http://172.16.100.230/plm-starter/modeling/index.html",
  "name" : "PSCorePrdFuncmodeling_ide_html_view",
  "getPSAppDataEntity" : {
    "modelref" : true,
    "path" : "PSSYSAPPS/plmweb/PSAPPDATAENTITIES/PSCorePrdFunc.json"
  },
  "getPSAppModule" : {
    "modelref" : true,
    "path" : "PSSYSAPPS/plmweb/PSAPPMODULES/extension.json"
  },
  "getPSAppViewEngines" : [ {
    "engineCat" : "VIEW",
    "engineType" : "HtmlView",
    "name" : "engine"
  } ],
  "getPSControls" : [ {
    "getCapPSLanguageRes" : {
      "lanResTag" : "DE.LNAME.PSCOREPRDFUNC"
    },
    "caption" : "核心产品功能",
    "codeName" : "modeling_ide_html_view_captionbar",
    "controlType" : "CAPTIONBAR",
    "name" : "captionbar",
    "getPSAppDataEntity" : {
      "modelref" : true,
      "path" : "PSSYSAPPS/plmweb/PSAPPDATAENTITIES/PSCorePrdFunc.json"
    },
    "getPSControlParam" : { }
  } ],
  "getPSDEViewCodeName" : "modeling_ide_html_view",
  "getPSDEViewId" : "7AB61711-C63E-4539-B458-6CB1F5916704",
  "getPSViewLayoutPanel" : {
    "codeName" : "layoutpanel",
    "controlStyle" : "APPDEHTMLVIEW",
    "controlType" : "VIEWLAYOUTPANEL",
    "name" : "layoutpanel",
    "getPSAppDataEntity" : {
      "modelref" : true,
      "path" : "PSSYSAPPS/plmweb/PSAPPDATAENTITIES/PSCorePrdFunc.json"
    },
    "getPSControlParam" : { },
    "layoutBodyOnly" : true,
    "layoutPanel" : true,
    "useDefaultLayout" : true
  },
  "title" : "ModelingIDEHTML",
  "viewStyle" : "DEFAULT",
  "viewType" : "DEHTMLVIEW",
  "enableDP" : true,
  "loadDefault" : true,
  "modelid" : "a9aea5c1e5646adad4c17e21629a7c5e",
  "modeltype" : "PSAPPDEVIEW"
}