{
  "codeListTag" : "CodeList118",
  "codeListType" : "STATIC",
  "codeName" : "CodeList118",
  "dynaInstMode" : 0,
  "dynaModelFilePath" : "PSCODELISTS/CodeList118.json",
  "emptyText" : "未定义",
  "name" : "平台内置处理组件类型",
  "getPSCodeItems" : [ {
    "codeName" : "Codelistfiller",
    "text" : "代码表填充器",
    "value" : "CODELISTFILLER"
  }, {
    "codeName" : "Wfprocess",
    "text" : "工作流嵌入处理",
    "value" : "WFPROCESS"
  }, {
    "codeName" : "Dgactionhelper",
    "text" : "表格后台处理对象",
    "value" : "DGACTIONHELPER"
  }, {
    "codeName" : "Formactionhelper",
    "text" : "表单后台处理类",
    "value" : "FORMACTIONHELPER"
  }, {
    "codeName" : "Page",
    "text" : "页面对象",
    "value" : "PAGE"
  } ],
  "getPSCodeListTemplId" : "CODELIST_02055",
  "refFlag" : false,
  "systemTag" : "iBizPLM",
  "codeItemValueNumber" : false,
  "enableCache" : true,
  "subSysAsCloud" : false,
  "subSysCodeList" : false,
  "userScope" : false
}