{
  "dBType" : "MYSQL5",
  "name" : "MySQL5",
  "getPSDEDataQueryCodeExps" : [ {
    "expression" : "t1.`CATEGORIES`",
    "name" : "CATEGORIES"
  }, {
    "expression" : "t1.`CHART_TYPE`",
    "name" : "CHART_TYPE"
  }, {
    "expression" : "t1.`CREATE_MAN`",
    "name" : "CREATE_MAN"
  }, {
    "expression" : "t1.`CREATE_TIME`",
    "name" : "CREATE_TIME"
  }, {
    "expression" : "t1.`DESC`",
    "name" : "DESC"
  }, {
    "expression" : "t1.`GROUP`",
    "name" : "GROUP"
  }, {
    "expression" : "t1.`ID`",
    "name" : "ID"
  }, {
    "expression" : "t1.`NAME`",
    "name" : "NAME"
  }, {
    "expression" : "t1.`UPDATE_MAN`",
    "name" : "UPDATE_MAN"
  }, {
    "expression" : "t1.`UPDATE_TIME`",
    "name" : "UPDATE_TIME"
  }, {
    "expression" : "t1.`VIEW_ID`",
    "name" : "VIEW_ID"
  } ],
  "queryCode" : "SELECT\nt1.`CATEGORIES`,\nt1.`CHART_TYPE`,\nt1.`CREATE_MAN`,\nt1.`CREATE_TIME`,\nt1.`DESC`,\nt1.`GROUP`,\nt1.`ID`,\nt1.`NAME`,\nt1.`UPDATE_MAN`,\nt1.`UPDATE_TIME`,\nt1.`VIEW_ID`\nFROM `INSIGHT_REPORT` t1 \n",
  "id" : "PSMODULES/Insight/PSDATAENTITIES/insight_report/PSDEDATAQUERIES/Default/PSDEDQCODES/MYSQL5.json"
}