{
  "codeName" : "UsrDRItem0920600876",
  "dynaModelFilePath" : "PSMODULES/ProjMgmt/PSDATAENTITIES/project/PSDEDRITEMS/UsrDRItem0920600876.json",
  "itemType" : "DER1N",
  "name" : "迭代移动端列表视图",
  "getPSDER" : {
    "modelref" : true,
    "path" : "PSMODULES/ProjMgmt/PSDATAENTITIES/sprint/PSDERS/DER1N_SPRINT_PROJECT_PROJECT_ID.json"
  },
  "parentDataJO" : {
    "SRFPARENTTYPE" : "DER1N",
    "srfparentdename" : "PROJECT",
    "srfparentmode" : "DER1N_SPRINT_PROJECT_PROJECT_ID",
    "srfparentdefname" : "PROJECT_ID",
    "SRFDER1NID" : "DER1N_SPRINT_PROJECT_PROJECT_ID"
  },
  "viewCodeName" : "mob_sprint_list_view",
  "getViewPSDataEntity" : {
    "modelref" : true,
    "path" : "PSMODULES/ProjMgmt/PSDATAENTITIES/sprint.json"
  },
  "viewParamJO" : {
    "SRFPARENTTYPE" : "DER1N",
    "SRFDER1NID" : "DER1N_SPRINT_PROJECT_PROJECT_ID"
  }
}