{
  "actionMode" : "CHECKKEY",
  "actionType" : "BUILTIN",
  "codeName" : "CheckKey",
  "dynaModelFilePath" : "PSMODULES/ProdMgmt/PSDATAENTITIES/ticket_type/PSDEACTIONS/CheckKey.json",
  "logicName" : "CheckKey",
  "name" : "CheckKey",
  "getPSDEActionInput" : {
    "name" : "CheckKeyInput",
    "getPSDEMethodDTO" : {
      "modelref" : true,
      "id" : "ticket_type_dto"
    },
    "type" : "DTO"
  },
  "getPSDEActionReturn" : {
    "name" : "CheckKeyResult",
    "stdDataType" : 9,
    "type" : "SIMPLE"
  },
  "builtinAction" : true
}