{
  "actionHolder" : 1,
  "actionMode" : "READ",
  "actionType" : "DELOGIC",
  "codeName" : "get_con_ticket",
  "dataAccessAction" : "READ",
  "dynaModelFilePath" : "PSMODULES/ProdMgmt/PSDATAENTITIES/ticket_type/PSDEACTIONS/get_con_ticket.json",
  "logicName" : "获取关联的工单",
  "name" : "get_con_ticket",
  "getPSDEActionInput" : {
    "getKeyPSDEField" : {
      "name" : "ID",
      "codeName" : "id"
    },
    "name" : "Get_con_ticketInput",
    "type" : "KEYFIELD"
  },
  "getPSDEActionReturn" : {
    "name" : "Get_con_ticketResult",
    "getPSDEMethodDTO" : {
      "modelref" : true,
      "id" : "ticket_type_dto"
    },
    "type" : "DTO"
  },
  "getPSDELogic" : {
    "modelref" : true,
    "path" : "PSMODULES/ProdMgmt/PSDATAENTITIES/ticket_type/PSDELOGICS/get_con_ticket.json"
  },
  "enableFront" : false
}