{
  "dBType" : "MYSQL5",
  "name" : "MySQL5",
  "getPSDEDataQueryCodeExps" : [ {
    "expression" : "t1.`BIMEASURETYPE`",
    "name" : "BIMEASURETYPE"
  }, {
    "expression" : "t1.`CODENAME`",
    "name" : "CODENAME"
  }, {
    "expression" : "t1.`DYNAMODELFLAG`",
    "name" : "DYNAMODELFLAG"
  }, {
    "expression" : "t1.`MEASUREFORMULA`",
    "name" : "MEASUREFORMULA"
  }, {
    "expression" : "t1.`MEMO`",
    "name" : "MEMO"
  }, {
    "expression" : "t1.`ORDERVALUE`",
    "name" : "ORDERVALUE"
  }, {
    "expression" : "t1.`PSSYSBICUBEID`",
    "name" : "PSSYSBICUBEID"
  }, {
    "expression" : "t1.`PSSYSBICUBEMEASUREID`",
    "name" : "PSSYSBICUBEMEASUREID"
  }, {
    "expression" : "t1.`PSSYSBICUBEMEASURENAME`",
    "name" : "PSSYSBICUBEMEASURENAME"
  }, {
    "expression" : "t1.`PSSYSBICUBENAME`",
    "name" : "PSSYSBICUBENAME"
  }, {
    "expression" : "t1.`PSSYSBISCHEMEID`",
    "name" : "PSSYSBISCHEMEID"
  }, {
    "expression" : "t1.`VALIDFLAG`",
    "name" : "VALIDFLAG"
  } ],
  "queryCode" : "SELECT\nt1.`BIMEASURETYPE`,\nt1.`CODENAME`,\nt1.`DYNAMODELFLAG`,\nt1.`MEASUREFORMULA`,\nt1.`MEMO`,\nt1.`ORDERVALUE`,\nt1.`PSSYSBICUBEID`,\nt1.`PSSYSBICUBEMEASUREID`,\nt1.`PSSYSBICUBEMEASURENAME`,\nt1.`PSSYSBICUBENAME`,\nt1.`PSSYSBISCHEMEID`,\nt1.`VALIDFLAG`\nFROM `` t1 \n",
  "id" : "PSMODULES/extension/PSDATAENTITIES/PSSysBICubeMeasure/PSDEDATAQUERIES/Default/PSDEDQCODES/MYSQL5.json"
}