{
  "autoSaveMode" : 1,
  "codeName" : "baseinfo_edit_view_form",
  "controlType" : "FORM",
  "getCreatePSControlAction" : {
    "modelref" : true,
    "id" : "create",
    "actionName" : "Create",
    "actionType" : "DEACTION",
    "dataAccessAction" : "CREATE",
    "name" : "create",
    "getPSAppDEMethod" : {
      "modelref" : true,
      "id" : "create"
    },
    "getPSAppDataEntity" : {
      "modelref" : true,
      "path" : "PSSYSAPPS/plmweb/PSAPPDATAENTITIES/insight_report.json"
    }
  },
  "defaultLabelWidth" : 130,
  "dynaModelFilePath" : "PSSYSAPPS/plmweb/PSAPPDATAENTITIES/insight_report/PSFORMS/baseinfo_edit_view_form.json",
  "getGetDraftFromPSControlAction" : {
    "modelref" : true,
    "id" : "loaddraftfrom",
    "actionName" : "GETDRAFTFROM",
    "actionType" : "DEACTION",
    "dataAccessAction" : "CREATE",
    "name" : "loaddraftfrom",
    "getPSAppDataEntity" : {
      "modelref" : true,
      "path" : "PSSYSAPPS/plmweb/PSAPPDATAENTITIES/insight_report.json"
    }
  },
  "getGetDraftPSControlAction" : {
    "modelref" : true,
    "id" : "loaddraft",
    "actionName" : "GetDraft",
    "actionType" : "DEACTION",
    "dataAccessAction" : "CREATE",
    "name" : "loaddraft",
    "getPSAppDEMethod" : {
      "modelref" : true,
      "id" : "get_draft"
    },
    "getPSAppDataEntity" : {
      "modelref" : true,
      "path" : "PSSYSAPPS/plmweb/PSAPPDATAENTITIES/insight_report.json"
    }
  },
  "getGetPSControlAction" : {
    "modelref" : true,
    "id" : "load",
    "actionName" : "Get",
    "actionType" : "DEACTION",
    "dataAccessAction" : "READ",
    "name" : "load",
    "getPSAppDEMethod" : {
      "modelref" : true,
      "id" : "get"
    },
    "getPSAppDataEntity" : {
      "modelref" : true,
      "path" : "PSSYSAPPS/plmweb/PSAPPDATAENTITIES/insight_report.json"
    }
  },
  "logicName" : "基础信息变更_表单",
  "getPSAppDataEntity" : {
    "modelref" : true,
    "path" : "PSSYSAPPS/plmweb/PSAPPDATAENTITIES/insight_report.json"
  },
  "getPSDEFormItems" : [ {
    "id" : "srfupdatedate",
    "hidden" : true,
    "dataType" : 5,
    "getPSAppDEField" : {
      "name" : "UPDATE_TIME",
      "codeName" : "update_time"
    }
  }, {
    "id" : "srforikey",
    "hidden" : true,
    "dataType" : 25
  }, {
    "id" : "srfkey",
    "hidden" : true,
    "dataType" : 25,
    "getPSAppDEField" : {
      "name" : "ID",
      "codeName" : "id"
    }
  }, {
    "id" : "srfmajortext",
    "hidden" : true,
    "dataType" : 25,
    "getPSAppDEField" : {
      "name" : "NAME",
      "codeName" : "name"
    }
  }, {
    "id" : "srftempmode",
    "hidden" : true,
    "dataType" : 25
  }, {
    "id" : "srfuf",
    "hidden" : true,
    "dataType" : 25
  }, {
    "id" : "srfdeid",
    "hidden" : true,
    "dataType" : 25
  }, {
    "id" : "srfsourcekey",
    "hidden" : true,
    "dataType" : 25
  }, {
    "id" : "name",
    "dataType" : 25,
    "getPSAppDEField" : {
      "name" : "NAME",
      "codeName" : "name"
    }
  }, {
    "id" : "chart_type",
    "dataType" : 25,
    "getPSAppDEField" : {
      "name" : "CHART_TYPE",
      "codeName" : "chart_type"
    }
  }, {
    "id" : "group",
    "dataType" : 25,
    "getPSAppDEField" : {
      "name" : "GROUP",
      "codeName" : "group"
    }
  }, {
    "id" : "template_model",
    "dataType" : 21,
    "getPSAppDEField" : {
      "name" : "TEMPLATE_MODEL",
      "codeName" : "template_model"
    }
  }, {
    "id" : "desc",
    "dataType" : 21,
    "getPSAppDEField" : {
      "name" : "DESC",
      "codeName" : "desc"
    }
  }, {
    "id" : "is_system",
    "dataType" : 9,
    "getPSAppDEField" : {
      "name" : "IS_SYSTEM",
      "codeName" : "is_system"
    }
  }, {
    "id" : "categories_name",
    "dataType" : 21,
    "getPSAppDEField" : {
      "name" : "CATEGORIES_NAME",
      "codeName" : "categories_name"
    }
  }, {
    "id" : "categories",
    "hidden" : true,
    "dataType" : 25,
    "getPSAppDEField" : {
      "name" : "CATEGORIES",
      "codeName" : "categories"
    }
  }, {
    "id" : "id",
    "hidden" : true,
    "dataType" : 25,
    "getPSAppDEField" : {
      "name" : "ID",
      "codeName" : "id"
    }
  } ],
  "getPSDEFormPages" : [ {
    "caption" : "基本信息",
    "codeName" : "formpage1",
    "detailStyle" : "DEFAULT",
    "detailType" : "FORMPAGE",
    "name" : "formpage1",
    "getPSDEFormDetails" : [ {
      "getCapPSLanguageRes" : {
        "lanResTag" : "DEF.LNAME.NAME"
      },
      "caption" : "名称",
      "codeName" : "name",
      "dataType" : 25,
      "detailStyle" : "DEFAULT",
      "detailType" : "FORMITEM",
      "enableCond" : 3,
      "ignoreInput" : 0,
      "labelPos" : "TOP",
      "labelWidth" : 130,
      "name" : "name",
      "noPrivDisplayMode" : 1,
      "getPSAppDEField" : {
        "name" : "NAME",
        "codeName" : "name"
      },
      "getPSEditor" : {
        "editorType" : "TEXTBOX",
        "maxLength" : 200,
        "name" : "name"
      },
      "getPSLayoutPos" : {
        "colMD" : 24,
        "layout" : "TABLE_24COL"
      },
      "allowEmpty" : true,
      "showCaption" : true
    }, {
      "caption" : "图表类型",
      "codeName" : "chart_type",
      "dataType" : 25,
      "detailStyle" : "DEFAULT",
      "detailType" : "FORMITEM",
      "enableCond" : 3,
      "ignoreInput" : 0,
      "labelPos" : "TOP",
      "labelWidth" : 130,
      "name" : "chart_type",
      "noPrivDisplayMode" : 1,
      "getPSAppDEField" : {
        "name" : "CHART_TYPE",
        "codeName" : "chart_type"
      },
      "getPSEditor" : {
        "editorType" : "DROPDOWNLIST",
        "name" : "chart_type",
        "getPSAppCodeList" : {
          "modelref" : true,
          "path" : "PSSYSAPPS/plmweb/PSAPPCODELISTS/Insight__bi_chart_type2.json"
        },
        "singleSelect" : true
      },
      "getPSLayoutPos" : {
        "colMD" : 24,
        "layout" : "TABLE_24COL"
      },
      "allowEmpty" : true,
      "needCodeListConfig" : true,
      "showCaption" : true
    }, {
      "caption" : "数据集",
      "codeName" : "group",
      "dataType" : 25,
      "detailStyle" : "DEFAULT",
      "detailType" : "FORMITEM",
      "enableCond" : 3,
      "ignoreInput" : 0,
      "labelPos" : "TOP",
      "labelWidth" : 130,
      "name" : "group",
      "noPrivDisplayMode" : 1,
      "getPSAppDEField" : {
        "name" : "GROUP",
        "codeName" : "group"
      },
      "getPSEditor" : {
        "editorType" : "DROPDOWNLIST",
        "name" : "group",
        "getPSAppCodeList" : {
          "modelref" : true,
          "path" : "PSSYSAPPS/plmweb/PSAPPCODELISTS/Insight__report_group_bi.json"
        },
        "singleSelect" : true
      },
      "getPSLayoutPos" : {
        "colMD" : 24,
        "layout" : "TABLE_24COL"
      },
      "allowEmpty" : true,
      "needCodeListConfig" : true,
      "showCaption" : true
    }, {
      "caption" : "模板模型",
      "codeName" : "template_model",
      "dataType" : 21,
      "detailStyle" : "DEFAULT",
      "detailType" : "FORMITEM",
      "enableCond" : 3,
      "ignoreInput" : 0,
      "itemHeight" : 220.0,
      "labelPos" : "TOP",
      "labelWidth" : 130,
      "name" : "template_model",
      "noPrivDisplayMode" : 1,
      "getPSAppDEField" : {
        "name" : "TEMPLATE_MODEL",
        "codeName" : "template_model"
      },
      "getPSEditor" : {
        "editorHeight" : 200.0,
        "editorParams" : {
          "HEIGHT" : "200"
        },
        "editorType" : "TEXTAREA_10",
        "maxLength" : 1048576,
        "name" : "template_model",
        "showMaxLength" : true
      },
      "getPSLayoutPos" : {
        "colMD" : 24,
        "layout" : "TABLE_24COL"
      },
      "allowEmpty" : true,
      "showCaption" : true
    }, {
      "caption" : "描述",
      "codeName" : "desc",
      "dataType" : 21,
      "detailStyle" : "DEFAULT",
      "detailType" : "FORMITEM",
      "enableCond" : 3,
      "ignoreInput" : 0,
      "itemHeight" : 220.0,
      "labelPos" : "TOP",
      "labelWidth" : 130,
      "name" : "desc",
      "noPrivDisplayMode" : 1,
      "getPSAppDEField" : {
        "name" : "DESC",
        "codeName" : "desc"
      },
      "getPSEditor" : {
        "editorHeight" : 200.0,
        "editorParams" : {
          "HEIGHT" : "200"
        },
        "editorType" : "TEXTAREA_10",
        "maxLength" : 1048576,
        "name" : "desc",
        "showMaxLength" : true
      },
      "getPSLayoutPos" : {
        "colMD" : 24,
        "layout" : "TABLE_24COL"
      },
      "allowEmpty" : true,
      "showCaption" : true
    }, {
      "caption" : "是否系统类型",
      "codeName" : "is_system",
      "dataType" : 9,
      "detailStyle" : "DEFAULT",
      "detailType" : "FORMITEM",
      "enableCond" : 3,
      "ignoreInput" : 0,
      "itemWidth" : 230.0,
      "labelPos" : "TOP",
      "labelWidth" : 130,
      "name" : "is_system",
      "noPrivDisplayMode" : 1,
      "getPSAppDEField" : {
        "name" : "IS_SYSTEM",
        "codeName" : "is_system"
      },
      "getPSEditor" : {
        "editorType" : "DROPDOWNLIST_100",
        "editorWidth" : 100.0,
        "name" : "is_system",
        "getPSAppCodeList" : {
          "modelref" : true,
          "path" : "PSSYSAPPS/plmweb/PSAPPCODELISTS/YesNo.json"
        },
        "singleSelect" : true
      },
      "getPSLayoutPos" : {
        "colMD" : 24,
        "layout" : "TABLE_24COL"
      },
      "allowEmpty" : true,
      "needCodeListConfig" : true,
      "showCaption" : true
    }, {
      "caption" : "类别",
      "codeName" : "categories_name",
      "dataType" : 21,
      "detailStyle" : "DEFAULT",
      "detailType" : "FORMITEM",
      "enableCond" : 3,
      "ignoreInput" : 0,
      "labelPos" : "TOP",
      "labelWidth" : 130,
      "name" : "categories_name",
      "noPrivDisplayMode" : 1,
      "getPSAppDEField" : {
        "name" : "CATEGORIES_NAME",
        "codeName" : "categories_name"
      },
      "getPSEditor" : {
        "editorParams" : {
          "srfnavparam.n_owner_id_eq" : "%insight_view%"
        },
        "editorType" : "DROPDOWNLIST",
        "name" : "categories_name",
        "getPSAppCodeList" : {
          "modelref" : true,
          "path" : "PSSYSAPPS/plmweb/PSAPPCODELISTS/ProdMgmt__category.json"
        },
        "getPSEditorItems" : [ {
          "name" : "categories"
        } ],
        "getPSNavigateParams" : [ {
          "key" : "n_owner_id_eq",
          "name" : "n_owner_id_eq",
          "value" : "insight_view",
          "rawValue" : false
        } ],
        "singleSelect" : true
      },
      "getPSLayoutPos" : {
        "colMD" : 24,
        "layout" : "TABLE_24COL"
      },
      "valueItemName" : "categories",
      "allowEmpty" : true,
      "needCodeListConfig" : true,
      "showCaption" : true
    }, {
      "caption" : "类别",
      "codeName" : "categories",
      "dataType" : 25,
      "detailStyle" : "DEFAULT",
      "detailType" : "FORMITEM",
      "enableCond" : 3,
      "ignoreInput" : 0,
      "labelPos" : "LEFT",
      "labelWidth" : 130,
      "name" : "categories",
      "noPrivDisplayMode" : 1,
      "getPSAppDEField" : {
        "name" : "CATEGORIES",
        "codeName" : "categories"
      },
      "getPSEditor" : {
        "editorType" : "HIDDEN",
        "name" : "categories"
      },
      "getPSLayoutPos" : {
        "colMD" : 24,
        "layout" : "TABLE_24COL"
      },
      "allowEmpty" : true,
      "hidden" : true
    }, {
      "getCapPSLanguageRes" : {
        "lanResTag" : "DEF.LNAME.ID"
      },
      "caption" : "标识",
      "codeName" : "id",
      "dataType" : 25,
      "detailStyle" : "DEFAULT",
      "detailType" : "FORMITEM",
      "enableCond" : 3,
      "ignoreInput" : 0,
      "labelPos" : "LEFT",
      "labelWidth" : 130,
      "name" : "id",
      "noPrivDisplayMode" : 1,
      "getPSAppDEField" : {
        "name" : "ID",
        "codeName" : "id"
      },
      "getPSEditor" : {
        "editorType" : "HIDDEN",
        "name" : "id"
      },
      "getPSLayoutPos" : {
        "colMD" : 24,
        "layout" : "TABLE_24COL"
      },
      "allowEmpty" : true,
      "hidden" : true
    } ],
    "getPSLayout" : {
      "childColMD" : 24,
      "columnCount" : 24,
      "layout" : "TABLE_24COL"
    },
    "infoGroupMode" : false
  } ],
  "getPSLayout" : {
    "childColMD" : 24,
    "columnCount" : 24,
    "layout" : "TABLE_24COL"
  },
  "getRemovePSControlAction" : {
    "modelref" : true,
    "id" : "remove",
    "actionName" : "Remove",
    "actionType" : "DEACTION",
    "dataAccessAction" : "DELETE",
    "name" : "remove",
    "getPSAppDEMethod" : {
      "modelref" : true,
      "id" : "remove"
    },
    "getPSAppDataEntity" : {
      "modelref" : true,
      "path" : "PSSYSAPPS/plmweb/PSAPPDATAENTITIES/insight_report.json"
    }
  },
  "tabHeaderPos" : "TOP",
  "getUpdatePSControlAction" : {
    "modelref" : true,
    "id" : "update",
    "actionName" : "Update",
    "actionType" : "DEACTION",
    "dataAccessAction" : "UPDATE",
    "name" : "update",
    "getPSAppDEMethod" : {
      "modelref" : true,
      "id" : "update"
    },
    "getPSAppDataEntity" : {
      "modelref" : true,
      "path" : "PSSYSAPPS/plmweb/PSAPPDATAENTITIES/insight_report.json"
    }
  },
  "enableAutoSave" : true,
  "noTabHeader" : true,
  "modelid" : "45A8FC0F-D4FB-41FF-888A-64C40B6BB597",
  "modeltype" : "PSDEFORM_EDITFORM"
}