{
  "codeName" : "simplelist",
  "controlStyle" : "LISTVIEW",
  "controlType" : "MOBMDCTRL",
  "getCreatePSControlAction" : {
    "modelref" : true,
    "id" : "create",
    "actionName" : "Create",
    "actionType" : "DEACTION",
    "dataAccessAction" : "CREATE",
    "name" : "create",
    "getPSAppDEMethod" : {
      "modelref" : true,
      "id" : "create"
    },
    "getPSAppDataEntity" : {
      "modelref" : true,
      "path" : "PSSYSAPPS/plmmob/PSAPPDATAENTITIES/member.json"
    }
  },
  "dynaModelFilePath" : "PSSYSAPPS/plmmob/PSAPPDATAENTITIES/member/PSMOBMDCTRLS/simplelist.json",
  "getFetchPSControlAction" : {
    "modelref" : true,
    "id" : "fetch",
    "actionType" : "DEDATASET",
    "name" : "fetch",
    "getPSAppDEMethod" : {
      "modelref" : true,
      "id" : "fetch_default"
    },
    "getPSAppDataEntity" : {
      "modelref" : true,
      "path" : "PSSYSAPPS/plmmob/PSAPPDATAENTITIES/member.json"
    }
  },
  "getGetPSControlAction" : {
    "modelref" : true,
    "id" : "load",
    "actionName" : "Get",
    "actionType" : "DEACTION",
    "dataAccessAction" : "READ",
    "name" : "load",
    "getPSAppDEMethod" : {
      "modelref" : true,
      "id" : "get"
    },
    "getPSAppDataEntity" : {
      "modelref" : true,
      "path" : "PSSYSAPPS/plmmob/PSAPPDATAENTITIES/member.json"
    }
  },
  "groupMode" : "NONE",
  "getItemPSLayoutPanel" : {
    "getAllPSPanelFields" : [ {
      "id" : "field_text_dynamic",
      "viewFieldName" : "ID"
    } ],
    "codeName" : "usr1016371843",
    "controlType" : "PANEL",
    "dynaModelFilePath" : "PSSYSAPPS/plmmob/PSAPPDATAENTITIES/member/PSPANELS/usr1016371843.json",
    "layoutMode" : "TABLE_24COL",
    "logicName" : "simplelist_列表项面板",
    "getPSAppDataEntity" : {
      "modelref" : true,
      "path" : "PSSYSAPPS/plmmob/PSAPPDATAENTITIES/member.json"
    },
    "getPSControlParam" : { },
    "getPSLayout" : {
      "childColMD" : 24,
      "columnCount" : 24,
      "layout" : "TABLE_24COL"
    },
    "getRootPSPanelItems" : [ {
      "itemStyle" : "DEFAULT",
      "itemType" : "CONTAINER",
      "name" : "page_container",
      "getPSLayout" : {
        "dir" : "column",
        "layout" : "FLEX"
      },
      "getPSLayoutPos" : {
        "colMD" : 24,
        "layout" : "TABLE_24COL"
      },
      "getPSPanelItems" : [ {
        "caption" : "文本(动态)",
        "itemStyle" : "DEFAULT",
        "itemType" : "FIELD",
        "name" : "field_text_dynamic",
        "getPSEditor" : {
          "editorType" : "SPAN",
          "name" : "field_text_dynamic",
          "predefinedType" : "FIELD_TEXT_DYNAMIC",
          "renderMode" : "TEXT_DYNAMIC",
          "enableLinkView" : false
        },
        "getPSLayoutPos" : {
          "grow" : -1,
          "layout" : "FLEX"
        },
        "viewFieldName" : "ID"
      } ]
    } ],
    "name" : "simplelist_itempanel",
    "modelid" : "1EEC7DFF-1780-4EF9-ACC2-0665D0E36E1D",
    "modeltype" : "PSSYSVIEWPANEL"
  },
  "logicName" : "simplelist",
  "mobListStyle" : "LISTVIEW",
  "getPSAppDataEntity" : {
    "modelref" : true,
    "path" : "PSSYSAPPS/plmmob/PSAPPDATAENTITIES/member.json"
  },
  "getPSDEListDataItems" : [ {
    "dataType" : 25,
    "name" : "srfkey",
    "getPSAppDEField" : {
      "name" : "ID",
      "codeName" : "id"
    }
  }, {
    "dataType" : 25,
    "name" : "srfmajortext",
    "getPSAppDEField" : {
      "name" : "NAME",
      "codeName" : "name"
    }
  }, {
    "dataType" : 25,
    "name" : "user_id",
    "getPSAppDEField" : {
      "name" : "USER_ID",
      "codeName" : "user_id"
    }
  } ],
  "pagingSize" : 1000,
  "getRemovePSControlAction" : {
    "modelref" : true,
    "id" : "remove",
    "actionName" : "Remove",
    "actionType" : "DEACTION",
    "dataAccessAction" : "DELETE",
    "name" : "remove",
    "getPSAppDEMethod" : {
      "modelref" : true,
      "id" : "remove"
    },
    "getPSAppDataEntity" : {
      "modelref" : true,
      "path" : "PSSYSAPPS/plmmob/PSAPPDATAENTITIES/member.json"
    }
  },
  "getUpdatePSControlAction" : {
    "modelref" : true,
    "id" : "update",
    "actionName" : "Update",
    "actionType" : "DEACTION",
    "dataAccessAction" : "UPDATE",
    "name" : "update",
    "getPSAppDEMethod" : {
      "modelref" : true,
      "id" : "update"
    },
    "getPSAppDataEntity" : {
      "modelref" : true,
      "path" : "PSSYSAPPS/plmmob/PSAPPDATAENTITIES/member.json"
    }
  },
  "hasWFDataItems" : false,
  "enableGroup" : false,
  "enableRowEdit" : false,
  "enableRowEditGroup" : false,
  "enableRowEditOrder" : false,
  "enableRowNew" : false,
  "noSort" : false,
  "showHeader" : true,
  "singleSelect" : false,
  "modelid" : "2D2DEA27-46CA-4E30-AB8D-1CCD040E0F4B",
  "modeltype" : "PSDELIST"
}