{
  "codeName" : "add_dependency",
  "defaultParamName" : "Default",
  "dynaModelFilePath" : "PSMODULES/Base/PSDATAENTITIES/relation/PSDELOGICS/add_dependency.json",
  "logicName" : "工作项添加依赖",
  "memo" : "工作项添加依赖",
  "name" : "工作项添加依赖",
  "getPSDELogicNodes" : [ {
    "codeName" : "Begin",
    "leftPos" : 154,
    "logicNodeType" : "BEGIN",
    "name" : "开始",
    "getPSDELogicLinks" : [ {
      "getDstPSDELogicNode" : {
        "modelref" : true,
        "id" : "BINDPARAM1"
      },
      "name" : "存在主要关联标识",
      "getPSDELogicLinkGroupCond" : {
        "groupOP" : "AND",
        "logicType" : "GROUP",
        "name" : "连接条件组",
        "getPSDELogicLinkConds" : [ {
          "condOP" : "ISNOTNULL",
          "dstFieldName" : "principal_id",
          "getDstLogicParam" : {
            "modelref" : true,
            "id" : "Default"
          },
          "logicType" : "SINGLE",
          "name" : "Default[principal_id] 值不为空(NotNil)"
        } ]
      },
      "getSrcPSDELogicNode" : {
        "modelref" : true,
        "id" : "Begin"
      }
    } ],
    "topPos" : -160
  }, {
    "codeName" : "BINDPARAM1",
    "getDstPSDELogicParam" : {
      "modelref" : true,
      "id" : "selectdata"
    },
    "leftPos" : 114,
    "logicNodeType" : "BINDPARAM",
    "name" : "绑定关联列表参数",
    "getPSDELogicLinks" : [ {
      "getDstPSDELogicNode" : {
        "modelref" : true,
        "id" : "LOOPSUBCALL1"
      },
      "name" : "存在选中数据",
      "getPSDELogicLinkGroupCond" : {
        "groupOP" : "AND",
        "logicType" : "GROUP",
        "name" : "连接条件组",
        "getPSDELogicLinkConds" : [ {
          "condOP" : "GT",
          "dstFieldName" : "size",
          "getDstLogicParam" : {
            "modelref" : true,
            "id" : "selectdata"
          },
          "logicType" : "SINGLE",
          "name" : "selectdata[size] 大于(>) 0",
          "paramValue" : "0"
        } ]
      },
      "getSrcPSDELogicNode" : {
        "modelref" : true,
        "id" : "BINDPARAM1"
      }
    } ],
    "srcFieldName" : "srfactionparam",
    "getSrcPSDELogicParam" : {
      "modelref" : true,
      "id" : "Default"
    },
    "topPos" : 140
  }, {
    "codeName" : "PREPAREPARAM1",
    "leftPos" : 680,
    "logicNodeType" : "PREPAREPARAM",
    "name" : "准备前置依赖参数",
    "getPSDELogicLinks" : [ {
      "getDstPSDELogicNode" : {
        "modelref" : true,
        "id" : "RAWSFCODE1"
      },
      "name" : "连接名称",
      "getSrcPSDELogicNode" : {
        "modelref" : true,
        "id" : "PREPAREPARAM1"
      }
    } ],
    "getPSDELogicNodeParams" : [ {
      "dstFieldName" : "PRINCIPAL_TYPE",
      "getDstPSDELogicParam" : {
        "modelref" : true,
        "id" : "dependency"
      },
      "name" : "直接值[dependency] ==> dependency[PRINCIPAL_TYPE]",
      "paramAction" : "SETPARAMVALUE",
      "srcValue" : "dependency",
      "srcValueType" : "SRCVALUE"
    }, {
      "dstFieldName" : "TARGET_ID",
      "getDstPSDELogicParam" : {
        "modelref" : true,
        "id" : "dependency"
      },
      "name" : "Default[PRINCIPAL_ID] ==> dependency[TARGET_ID]",
      "paramAction" : "SETPARAMVALUE",
      "srcFieldName" : "PRINCIPAL_ID",
      "getSrcPSDELogicParam" : {
        "modelref" : true,
        "id" : "Default"
      },
      "srcValueType" : "SRCDLPARAM"
    }, {
      "dstFieldName" : "RELATION_TYPE",
      "getDstPSDELogicParam" : {
        "modelref" : true,
        "id" : "dependency"
      },
      "name" : "直接值[1] ==> dependency[RELATION_TYPE]",
      "paramAction" : "SETPARAMVALUE",
      "srcValue" : "1",
      "srcValueType" : "SRCVALUE"
    } ],
    "topPos" : 180
  }, {
    "code" : "def for_temp_obj = logic.param('for_temp_obj').getReal()\r\n\r\ndef dependency = logic.param('dependency').getReal()\r\n\r\n\r\n// PC端 target_id   mob端 使用id \r\nif(for_temp_obj.get('id') != null){\r\n    dependency.set('principal_id', for_temp_obj.get('id'))\r\n}\r\nif(for_temp_obj.get('target_id') != null){\r\n    dependency.set('principal_id', for_temp_obj.get('target_id'))\r\n}\r\n\r\n\r\n",
    "codeName" : "RAWSFCODE1",
    "codeType" : "Groovy",
    "leftPos" : 854,
    "logicNodeType" : "RAWSFCODE",
    "name" : "填充principal_id",
    "getPSDELogicLinks" : [ {
      "getDstPSDELogicNode" : {
        "modelref" : true,
        "id" : "DEACTION1"
      },
      "name" : "连接名称",
      "getSrcPSDELogicNode" : {
        "modelref" : true,
        "id" : "RAWSFCODE1"
      }
    } ],
    "topPos" : 180
  }, {
    "codeName" : "LOOPSUBCALL1",
    "getDstPSDELogicParam" : {
      "modelref" : true,
      "id" : "for_temp_obj"
    },
    "leftPos" : 114,
    "logicNodeType" : "LOOPSUBCALL",
    "name" : "循环子调用",
    "getPSDELogicLinks" : [ {
      "getDstPSDELogicNode" : {
        "modelref" : true,
        "id" : "RENEWPARAM1"
      },
      "name" : "进入循环",
      "getSrcPSDELogicNode" : {
        "modelref" : true,
        "id" : "LOOPSUBCALL1"
      },
      "subCallLink" : true
    }, {
      "getDstPSDELogicNode" : {
        "modelref" : true,
        "id" : "END1"
      },
      "name" : "循环结束",
      "getSrcPSDELogicNode" : {
        "modelref" : true,
        "id" : "LOOPSUBCALL1"
      }
    } ],
    "getSrcPSDELogicParam" : {
      "modelref" : true,
      "id" : "selectdata"
    },
    "topPos" : 300
  }, {
    "codeName" : "RENEWPARAM1",
    "getDstPSDELogicParam" : {
      "modelref" : true,
      "id" : "dependency"
    },
    "leftPos" : 436,
    "logicNodeType" : "RENEWPARAM",
    "name" : "重新建立循环临时参数",
    "getPSDELogicLinks" : [ {
      "getDstPSDELogicNode" : {
        "modelref" : true,
        "id" : "PREPAREPARAM2"
      },
      "name" : "后置任务",
      "getPSDELogicLinkGroupCond" : {
        "groupOP" : "AND",
        "logicType" : "GROUP",
        "name" : "连接条件组",
        "getPSDELogicLinkConds" : [ {
          "condOP" : "EQ",
          "dstFieldName" : "RELATION_TYPE",
          "getDstLogicParam" : {
            "modelref" : true,
            "id" : "Default"
          },
          "logicType" : "SINGLE",
          "name" : "Default[RELATION_TYPE] 等于(=) after",
          "paramValue" : "after"
        } ]
      },
      "getSrcPSDELogicNode" : {
        "modelref" : true,
        "id" : "RENEWPARAM1"
      }
    }, {
      "getDstPSDELogicNode" : {
        "modelref" : true,
        "id" : "PREPAREPARAM1"
      },
      "name" : "前置任务",
      "getPSDELogicLinkGroupCond" : {
        "groupOP" : "AND",
        "logicType" : "GROUP",
        "name" : "连接条件组",
        "getPSDELogicLinkConds" : [ {
          "condOP" : "EQ",
          "dstFieldName" : "RELATION_TYPE",
          "getDstLogicParam" : {
            "modelref" : true,
            "id" : "Default"
          },
          "logicType" : "SINGLE",
          "name" : "Default[RELATION_TYPE] 等于(=) front",
          "paramValue" : "front"
        } ]
      },
      "getSrcPSDELogicNode" : {
        "modelref" : true,
        "id" : "RENEWPARAM1"
      }
    } ],
    "topPos" : 300
  }, {
    "codeName" : "DEACTION1",
    "getDstPSDEAction" : {
      "modelref" : true,
      "path" : "PSMODULES/Base/PSDATAENTITIES/relation/PSDEACTIONS/Save.json"
    },
    "getDstPSDELogicParam" : {
      "modelref" : true,
      "id" : "dependency"
    },
    "getDstPSDataEntity" : {
      "modelref" : true,
      "path" : "PSMODULES/Base/PSDATAENTITIES/relation.json"
    },
    "leftPos" : 1132,
    "logicNodeType" : "DEACTION",
    "name" : "添加依赖",
    "topPos" : 300
  }, {
    "codeName" : "PREPAREPARAM2",
    "leftPos" : 680,
    "logicNodeType" : "PREPAREPARAM",
    "name" : "准备后置依赖参数",
    "getPSDELogicLinks" : [ {
      "getDstPSDELogicNode" : {
        "modelref" : true,
        "id" : "RAWSFCODE2"
      },
      "name" : "连接名称",
      "getSrcPSDELogicNode" : {
        "modelref" : true,
        "id" : "PREPAREPARAM2"
      }
    } ],
    "getPSDELogicNodeParams" : [ {
      "dstFieldName" : "PRINCIPAL_TYPE",
      "getDstPSDELogicParam" : {
        "modelref" : true,
        "id" : "dependency"
      },
      "name" : "直接值[dependency] ==> dependency[PRINCIPAL_TYPE]",
      "paramAction" : "SETPARAMVALUE",
      "srcValue" : "dependency",
      "srcValueType" : "SRCVALUE"
    }, {
      "dstFieldName" : "RELATION_TYPE",
      "getDstPSDELogicParam" : {
        "modelref" : true,
        "id" : "dependency"
      },
      "name" : "直接值[1] ==> dependency[RELATION_TYPE]",
      "paramAction" : "SETPARAMVALUE",
      "srcValue" : "1",
      "srcValueType" : "SRCVALUE"
    }, {
      "dstFieldName" : "PRINCIPAL_ID",
      "getDstPSDELogicParam" : {
        "modelref" : true,
        "id" : "dependency"
      },
      "name" : "Default[PRINCIPAL_ID] ==> dependency[PRINCIPAL_ID]",
      "paramAction" : "SETPARAMVALUE",
      "srcFieldName" : "PRINCIPAL_ID",
      "getSrcPSDELogicParam" : {
        "modelref" : true,
        "id" : "Default"
      },
      "srcValueType" : "SRCDLPARAM"
    } ],
    "topPos" : 350
  }, {
    "code" : "def for_temp_obj = logic.param('for_temp_obj').getReal()\r\n\r\ndef dependency = logic.param('dependency').getReal()\r\n\r\n\r\n// PC端 使用target_id   mob端 使用id \r\nif(for_temp_obj.get('id') != null){\r\n    dependency.set('target_id', for_temp_obj.get('id'))\r\n}\r\nif(for_temp_obj.get('target_id') != null){\r\n    dependency.set('target_id', for_temp_obj.get('target_id'))\r\n}\r\n\r\n\r\n",
    "codeName" : "RAWSFCODE2",
    "codeType" : "Groovy",
    "leftPos" : 854,
    "logicNodeType" : "RAWSFCODE",
    "name" : "填充target_id",
    "getPSDELogicLinks" : [ {
      "getDstPSDELogicNode" : {
        "modelref" : true,
        "id" : "DEACTION1"
      },
      "name" : "连接名称",
      "getSrcPSDELogicNode" : {
        "modelref" : true,
        "id" : "RAWSFCODE2"
      }
    } ],
    "topPos" : 350
  }, {
    "codeName" : "END1",
    "leftPos" : 154,
    "logicNodeType" : "END",
    "name" : "结束",
    "getReturnParam" : {
      "modelref" : true,
      "id" : "Default"
    },
    "returnType" : "LOGICPARAM",
    "topPos" : 654
  } ],
  "getPSDELogicParams" : [ {
    "codeName" : "Default",
    "logicName" : "传入变量",
    "name" : "传入变量",
    "getParamPSDataEntity" : {
      "modelref" : true,
      "path" : "PSMODULES/Base/PSDATAENTITIES/relation.json"
    },
    "default" : true,
    "entityParam" : true
  }, {
    "codeName" : "dependency",
    "logicName" : "依赖",
    "name" : "依赖",
    "getParamPSDataEntity" : {
      "modelref" : true,
      "path" : "PSMODULES/Base/PSDATAENTITIES/relation.json"
    },
    "entityParam" : true
  }, {
    "codeName" : "for_temp_obj",
    "logicName" : "循环临时变量",
    "name" : "循环临时变量",
    "getParamPSDataEntity" : {
      "modelref" : true,
      "path" : "PSMODULES/Base/PSDATAENTITIES/relation.json"
    },
    "entityParam" : true
  }, {
    "codeName" : "selectdata",
    "logicName" : "关联列表",
    "name" : "关联列表",
    "getParamPSDataEntity" : {
      "modelref" : true,
      "path" : "PSMODULES/Base/PSDATAENTITIES/relation.json"
    },
    "entityListParam" : true
  } ],
  "getStartPSDELogicNode" : {
    "modelref" : true,
    "id" : "Begin"
  },
  "enableBackend" : true,
  "enableFront" : false
}